{
  "problem": {
    "name": "att532",
    "type": "TSP",
    "comment": "532-city problem (Padberg/Rinaldi)",
    "dimension": 532,
    "capacity": null,
    "edge_weight_type": "ATT",
    "edge_weight_format": null,
    "node_coord_type": null,
    "display_data_type": null,
    "file_path": "datasets_raw/problems/tsp/att532.tsp",
    "file_size": 7391
  },
  "nodes": [
    {
      "node_id": 0,
      "x": 7810,
      "y": 6053,
      "z": null,
      "demand": 0,
      "is_depot": false,
      "display_x": null,
      "display_y": null
    },
    {
      "node_id": 1,
      "x": 7798,
      "y": 5709,
      "z": null,
      "demand": 0,
      "is_depot": false,
      "display_x": null,
      "display_y": null
    },
    {
      "node_id": 2,
      "x": 7264,
      "y": 5575,
      "z": null,
      "demand": 0,
      "is_depot": false,
      "display_x": null,
      "display_y": null
    },
    {
      "node_id": 3,
      "x": 7324,
      "y": 5560,
      "z": null,
      "demand": 0,
      "is_depot": false,
      "display_x": null,
      "display_y": null
    },
    {
      "node_id": 4,
      "x": 7547,
      "y": 5503,
      "z": null,
      "demand": 0,
      "is_depot": false,
      "display_x": null,
      "display_y": null
    },
    {
      "node_id": 5,
      "x": 7744,
      "y": 5476,
      "z": null,
      "demand": 0,
      "is_depot": false,
      "display_x": null,
      "display_y": null
    },
    {
      "node_id": 6,
      "x": 7821,
      "y": 5457,
      "z": null,
      "demand": 0,
      "is_depot": false,
      "display_x": null,
      "display_y": null
    },
    {
      "node_id": 7,
      "x": 7883,
      "y": 5408,
      "z": null,
      "demand": 0,
      "is_depot": false,
      "display_x": null,
      "display_y": null
    },
    {
      "node_id": 8,
      "x": 7874,
      "y": 5405,
      "z": null,
      "demand": 0,
      "is_depot": false,
      "display_x": null,
      "display_y": null
    },
    {
      "node_id": 9,
      "x": 7927,
      "y": 5365,
      "z": null,
      "demand": 0,
      "is_depot": false,
      "display_x": null,
      "display_y": null
    },
    {
      "node_id": 10,
      "x": 7848,
      "y": 5358,
      "z": null,
      "demand": 0,
      "is_depot": false,
      "display_x": null,
      "display_y": null
    },
    {
      "node_id": 11,
      "x": 7802,
      "y": 5317,
      "z": null,
      "demand": 0,
      "is_depot": false,
      "display_x": null,
      "display_y": null
    },
    {
      "node_id": 12,
      "x": 7962,
      "y": 5287,
      "z": null,
      "demand": 0,
      "is_depot": false,
      "display_x": null,
      "display_y": null
    },
    {
      "node_id": 13,
      "x": 7913,
      "y": 5280,
      "z": null,
      "demand": 0,
      "is_depot": false,
      "display_x": null,
      "display_y": null
    },
    {
      "node_id": 14,
      "x": 7724,
      "y": 5210,
      "z": null,
      "demand": 0,
      "is_depot": false,
      "display_x": null,
      "display_y": null
    },
    {
      "node_id": 15,
      "x": 7503,
      "y": 5191,
      "z": null,
      "demand": 0,
      "is_depot": false,
      "display_x": null,
      "display_y": null
    },
    {
      "node_id": 16,
      "x": 7759,
      "y": 5143,
      "z": null,
      "demand": 0,
      "is_depot": false,
      "display_x": null,
      "display_y": null
    },
    {
      "node_id": 17,
      "x": 7890,
      "y": 5130,
      "z": null,
      "demand": 0,
      "is_depot": false,
      "display_x": null,
      "display_y": null
    },
    {
      "node_id": 18,
      "x": 7254,
      "y": 5129,
      "z": null,
      "demand": 0,
      "is_depot": false,
      "display_x": null,
      "display_y": null
    },
    {
      "node_id": 19,
      "x": 7790,
      "y": 5038,
      "z": null,
      "demand": 0,
      "is_depot": false,
      "display_x": null,
      "display_y": null
    },
    {
      "node_id": 20,
      "x": 7142,
      "y": 5032,
      "z": null,
      "demand": 0,
      "is_depot": false,
      "display_x": null,
      "display_y": null
    },
    {
      "node_id": 21,
      "x": 7606,
      "y": 5009,
      "z": null,
      "demand": 0,
      "is_depot": false,
      "display_x": null,
      "display_y": null
    },
    {
      "node_id": 22,
      "x": 7772,
      "y": 4989,
      "z": null,
      "demand": 0,
      "is_depot": false,
      "display_x": null,
      "display_y": null
    },
    {
      "node_id": 23,
      "x": 7744,
      "y": 4933,
      "z": null,
      "demand": 0,
      "is_depot": false,
      "display_x": null,
      "display_y": null
    },
    {
      "node_id": 24,
      "x": 7846,
      "y": 4923,
      "z": null,
      "demand": 0,
      "is_depot": false,
      "display_x": null,
      "display_y": null
    },
    {
      "node_id": 25,
      "x": 7622,
      "y": 4917,
      "z": null,
      "demand": 0,
      "is_depot": false,
      "display_x": null,
      "display_y": null
    },
    {
      "node_id": 26,
      "x": 6937,
      "y": 4917,
      "z": null,
      "demand": 0,
      "is_depot": false,
      "display_x": null,
      "display_y": null
    },
    {
      "node_id": 27,
      "x": 7576,
      "y": 4915,
      "z": null,
      "demand": 0,
      "is_depot": false,
      "display_x": null,
      "display_y": null
    },
    {
      "node_id": 28,
      "x": 7783,
      "y": 4912,
      "z": null,
      "demand": 0,
      "is_depot": false,
      "display_x": null,
      "display_y": null
    },
    {
      "node_id": 29,
      "x": 7716,
      "y": 4909,
      "z": null,
      "demand": 0,
      "is_depot": false,
      "display_x": null,
      "display_y": null
    },
    {
      "node_id": 30,
      "x": 7295,
      "y": 4887,
      "z": null,
      "demand": 0,
      "is_depot": false,
      "display_x": null,
      "display_y": null
    },
    {
      "node_id": 31,
      "x": 7777,
      "y": 4869,
      "z": null,
      "demand": 0,
      "is_depot": false,
      "display_x": null,
      "display_y": null
    },
    {
      "node_id": 32,
      "x": 7700,
      "y": 4854,
      "z": null,
      "demand": 0,
      "is_depot": false,
      "display_x": null,
      "display_y": null
    },
    {
      "node_id": 33,
      "x": 7726,
      "y": 4833,
      "z": null,
      "demand": 0,
      "is_depot": false,
      "display_x": null,
      "display_y": null
    },
    {
      "node_id": 34,
      "x": 7702,
      "y": 4815,
      "z": null,
      "demand": 0,
      "is_depot": false,
      "display_x": null,
      "display_y": null
    },
    {
      "node_id": 35,
      "x": 7583,
      "y": 4813,
      "z": null,
      "demand": 0,
      "is_depot": false,
      "display_x": null,
      "display_y": null
    },
    {
      "node_id": 36,
      "x": 7654,
      "y": 4795,
      "z": null,
      "demand": 0,
      "is_depot": false,
      "display_x": null,
      "display_y": null
    },
    {
      "node_id": 37,
      "x": 7417,
      "y": 4788,
      "z": null,
      "demand": 0,
      "is_depot": false,
      "display_x": null,
      "display_y": null
    },
    {
      "node_id": 38,
      "x": 7267,
      "y": 4779,
      "z": null,
      "demand": 0,
      "is_depot": false,
      "display_x": null,
      "display_y": null
    },
    {
      "node_id": 39,
      "x": 6806,
      "y": 4755,
      "z": null,
      "demand": 0,
      "is_depot": false,
      "display_x": null,
      "display_y": null
    },
    {
      "node_id": 40,
      "x": 5259,
      "y": 4751,
      "z": null,
      "demand": 0,
      "is_depot": false,
      "display_x": null,
      "display_y": null
    },
    {
      "node_id": 41,
      "x": 7698,
      "y": 4745,
      "z": null,
      "demand": 0,
      "is_depot": false,
      "display_x": null,
      "display_y": null
    },
    {
      "node_id": 42,
      "x": 7570,
      "y": 4741,
      "z": null,
      "demand": 0,
      "is_depot": false,
      "display_x": null,
      "display_y": null
    },
    {
      "node_id": 43,
      "x": 7617,
      "y": 4724,
      "z": null,
      "demand": 0,
      "is_depot": false,
      "display_x": null,
      "display_y": null
    },
    {
      "node_id": 44,
      "x": 7752,
      "y": 4721,
      "z": null,
      "demand": 0,
      "is_depot": false,
      "display_x": null,
      "display_y": null
    },
    {
      "node_id": 45,
      "x": 7673,
      "y": 4718,
      "z": null,
      "demand": 0,
      "is_depot": false,
      "display_x": null,
      "display_y": null
    },
    {
      "node_id": 46,
      "x": 7692,
      "y": 4666,
      "z": null,
      "demand": 0,
      "is_depot": false,
      "display_x": null,
      "display_y": null
    },
    {
      "node_id": 47,
      "x": 7547,
      "y": 4664,
      "z": null,
      "demand": 0,
      "is_depot": false,
      "display_x": null,
      "display_y": null
    },
    {
      "node_id": 48,
      "x": 7259,
      "y": 4630,
      "z": null,
      "demand": 0,
      "is_depot": false,
      "display_x": null,
      "display_y": null
    },
    {
      "node_id": 49,
      "x": 5387,
      "y": 4623,
      "z": null,
      "demand": 0,
      "is_depot": false,
      "display_x": null,
      "display_y": null
    },
    {
      "node_id": 50,
      "x": 7679,
      "y": 4581,
      "z": null,
      "demand": 0,
      "is_depot": false,
      "display_x": null,
      "display_y": null
    },
    {
      "node_id": 51,
      "x": 7674,
      "y": 4579,
      "z": null,
      "demand": 0,
      "is_depot": false,
      "display_x": null,
      "display_y": null
    },
    {
      "node_id": 52,
      "x": 7631,
      "y": 4573,
      "z": null,
      "demand": 0,
      "is_depot": false,
      "display_x": null,
      "display_y": null
    },
    {
      "node_id": 53,
      "x": 7520,
      "y": 4572,
      "z": null,
      "demand": 0,
      "is_depot": false,
      "display_x": null,
      "display_y": null
    },
    {
      "node_id": 54,
      "x": 7848,
      "y": 4546,
      "z": null,
      "demand": 0,
      "is_depot": false,
      "display_x": null,
      "display_y": null
    },
    {
      "node_id": 55,
      "x": 5685,
      "y": 4546,
      "z": null,
      "demand": 0,
      "is_depot": false,
      "display_x": null,
      "display_y": null
    },
    {
      "node_id": 56,
      "x": 7832,
      "y": 4542,
      "z": null,
      "demand": 0,
      "is_depot": false,
      "display_x": null,
      "display_y": null
    },
    {
      "node_id": 57,
      "x": 6735,
      "y": 4509,
      "z": null,
      "demand": 0,
      "is_depot": false,
      "display_x": null,
      "display_y": null
    },
    {
      "node_id": 58,
      "x": 7647,
      "y": 4504,
      "z": null,
      "demand": 0,
      "is_depot": false,
      "display_x": null,
      "display_y": null
    },
    {
      "node_id": 59,
      "x": 7338,
      "y": 4481,
      "z": null,
      "demand": 0,
      "is_depot": false,
      "display_x": null,
      "display_y": null
    },
    {
      "node_id": 60,
      "x": 4602,
      "y": 4478,
      "z": null,
      "demand": 0,
      "is_depot": false,
      "display_x": null,
      "display_y": null
    },
    {
      "node_id": 61,
      "x": 4606,
      "y": 4468,
      "z": null,
      "demand": 0,
      "is_depot": false,
      "display_x": null,
      "display_y": null
    },
    {
      "node_id": 62,
      "x": 7399,
      "y": 4467,
      "z": null,
      "demand": 0,
      "is_depot": false,
      "display_x": null,
      "display_y": null
    },
    {
      "node_id": 63,
      "x": 7037,
      "y": 4446,
      "z": null,
      "demand": 0,
      "is_depot": false,
      "display_x": null,
      "display_y": null
    },
    {
      "node_id": 64,
      "x": 7458,
      "y": 4428,
      "z": null,
      "demand": 0,
      "is_depot": false,
      "display_x": null,
      "display_y": null
    },
    {
      "node_id": 65,
      "x": 7364,
      "y": 4427,
      "z": null,
      "demand": 0,
      "is_depot": false,
      "display_x": null,
      "display_y": null
    },
    {
      "node_id": 66,
      "x": 6058,
      "y": 4426,
      "z": null,
      "demand": 0,
      "is_depot": false,
      "display_x": null,
      "display_y": null
    },
    {
      "node_id": 67,
      "x": 6868,
      "y": 4418,
      "z": null,
      "demand": 0,
      "is_depot": false,
      "display_x": null,
      "display_y": null
    },
    {
      "node_id": 68,
      "x": 3832,
      "y": 4410,
      "z": null,
      "demand": 0,
      "is_depot": false,
      "display_x": null,
      "display_y": null
    },
    {
      "node_id": 69,
      "x": 6670,
      "y": 4401,
      "z": null,
      "demand": 0,
      "is_depot": false,
      "display_x": null,
      "display_y": null
    },
    {
      "node_id": 70,
      "x": 7443,
      "y": 4375,
      "z": null,
      "demand": 0,
      "is_depot": false,
      "display_x": null,
      "display_y": null
    },
    {
      "node_id": 71,
      "x": 7160,
      "y": 4370,
      "z": null,
      "demand": 0,
      "is_depot": false,
      "display_x": null,
      "display_y": null
    },
    {
      "node_id": 72,
      "x": 6139,
      "y": 4369,
      "z": null,
      "demand": 0,
      "is_depot": false,
      "display_x": null,
      "display_y": null
    },
    {
      "node_id": 73,
      "x": 7333,
      "y": 4335,
      "z": null,
      "demand": 0,
      "is_depot": false,
      "display_x": null,
      "display_y": null
    },
    {
      "node_id": 74,
      "x": 6237,
      "y": 4332,
      "z": null,
      "demand": 0,
      "is_depot": false,
      "display_x": null,
      "display_y": null
    },
    {
      "node_id": 75,
      "x": 5385,
      "y": 4318,
      "z": null,
      "demand": 0,
      "is_depot": false,
      "display_x": null,
      "display_y": null
    },
    {
      "node_id": 76,
      "x": 6911,
      "y": 4296,
      "z": null,
      "demand": 0,
      "is_depot": false,
      "display_x": null,
      "display_y": null
    },
    {
      "node_id": 77,
      "x": 6304,
      "y": 4294,
      "z": null,
      "demand": 0,
      "is_depot": false,
      "display_x": null,
      "display_y": null
    },
    {
      "node_id": 78,
      "x": 7111,
      "y": 4288,
      "z": null,
      "demand": 0,
      "is_depot": false,
      "display_x": null,
      "display_y": null
    },
    {
      "node_id": 79,
      "x": 6740,
      "y": 4282,
      "z": null,
      "demand": 0,
      "is_depot": false,
      "display_x": null,
      "display_y": null
    },
    {
      "node_id": 80,
      "x": 7698,
      "y": 4279,
      "z": null,
      "demand": 0,
      "is_depot": false,
      "display_x": null,
      "display_y": null
    },
    {
      "node_id": 81,
      "x": 7613,
      "y": 4275,
      "z": null,
      "demand": 0,
      "is_depot": false,
      "display_x": null,
      "display_y": null
    },
    {
      "node_id": 82,
      "x": 7360,
      "y": 4275,
      "z": null,
      "demand": 0,
      "is_depot": false,
      "display_x": null,
      "display_y": null
    },
    {
      "node_id": 83,
      "x": 6779,
      "y": 4273,
      "z": null,
      "demand": 0,
      "is_depot": false,
      "display_x": null,
      "display_y": null
    },
    {
      "node_id": 84,
      "x": 7207,
      "y": 4270,
      "z": null,
      "demand": 0,
      "is_depot": false,
      "display_x": null,
      "display_y": null
    },
    {
      "node_id": 85,
      "x": 6241,
      "y": 4268,
      "z": null,
      "demand": 0,
      "is_depot": false,
      "display_x": null,
      "display_y": null
    },
    {
      "node_id": 86,
      "x": 7432,
      "y": 4265,
      "z": null,
      "demand": 0,
      "is_depot": false,
      "display_x": null,
      "display_y": null
    },
    {
      "node_id": 87,
      "x": 4354,
      "y": 4262,
      "z": null,
      "demand": 0,
      "is_depot": false,
      "display_x": null,
      "display_y": null
    },
    {
      "node_id": 88,
      "x": 6589,
      "y": 4256,
      "z": null,
      "demand": 0,
      "is_depot": false,
      "display_x": null,
      "display_y": null
    },
    {
      "node_id": 89,
      "x": 7817,
      "y": 4252,
      "z": null,
      "demand": 0,
      "is_depot": false,
      "display_x": null,
      "display_y": null
    },
    {
      "node_id": 90,
      "x": 6051,
      "y": 4246,
      "z": null,
      "demand": 0,
      "is_depot": false,
      "display_x": null,
      "display_y": null
    },
    {
      "node_id": 91,
      "x": 5356,
      "y": 4241,
      "z": null,
      "demand": 0,
      "is_depot": false,
      "display_x": null,
      "display_y": null
    },
    {
      "node_id": 92,
      "x": 7554,
      "y": 4236,
      "z": null,
      "demand": 0,
      "is_depot": false,
      "display_x": null,
      "display_y": null
    },
    {
      "node_id": 93,
      "x": 7534,
      "y": 4227,
      "z": null,
      "demand": 0,
      "is_depot": false,
      "display_x": null,
      "display_y": null
    },
    {
      "node_id": 94,
      "x": 4217,
      "y": 4224,
      "z": null,
      "demand": 0,
      "is_depot": false,
      "display_x": null,
      "display_y": null
    },
    {
      "node_id": 95,
      "x": 7349,
      "y": 4219,
      "z": null,
      "demand": 0,
      "is_depot": false,
      "display_x": null,
      "display_y": null
    },
    {
      "node_id": 96,
      "x": 7128,
      "y": 4215,
      "z": null,
      "demand": 0,
      "is_depot": false,
      "display_x": null,
      "display_y": null
    },
    {
      "node_id": 97,
      "x": 3950,
      "y": 4215,
      "z": null,
      "demand": 0,
      "is_depot": false,
      "display_x": null,
      "display_y": null
    },
    {
      "node_id": 98,
      "x": 6947,
      "y": 4209,
      "z": null,
      "demand": 0,
      "is_depot": false,
      "display_x": null,
      "display_y": null
    },
    {
      "node_id": 99,
      "x": 7549,
      "y": 4208,
      "z": null,
      "demand": 0,
      "is_depot": false,
      "display_x": null,
      "display_y": null
    },
    {
      "node_id": 100,
      "x": 5168,
      "y": 4208,
      "z": null,
      "demand": 0,
      "is_depot": false,
      "display_x": null,
      "display_y": null
    },
    {
      "node_id": 101,
      "x": 6524,
      "y": 4207,
      "z": null,
      "demand": 0,
      "is_depot": false,
      "display_x": null,
      "display_y": null
    },
    {
      "node_id": 102,
      "x": 5871,
      "y": 4202,
      "z": null,
      "demand": 0,
      "is_depot": false,
      "display_x": null,
      "display_y": null
    },
    {
      "node_id": 103,
      "x": 7542,
      "y": 4198,
      "z": null,
      "demand": 0,
      "is_depot": false,
      "display_x": null,
      "display_y": null
    },
    {
      "node_id": 104,
      "x": 6660,
      "y": 4193,
      "z": null,
      "demand": 0,
      "is_depot": false,
      "display_x": null,
      "display_y": null
    },
    {
      "node_id": 105,
      "x": 7216,
      "y": 4180,
      "z": null,
      "demand": 0,
      "is_depot": false,
      "display_x": null,
      "display_y": null
    },
    {
      "node_id": 106,
      "x": 6607,
      "y": 4173,
      "z": null,
      "demand": 0,
      "is_depot": false,
      "display_x": null,
      "display_y": null
    },
    {
      "node_id": 107,
      "x": 7601,
      "y": 4171,
      "z": null,
      "demand": 0,
      "is_depot": false,
      "display_x": null,
      "display_y": null
    },
    {
      "node_id": 108,
      "x": 6123,
      "y": 4167,
      "z": null,
      "demand": 0,
      "is_depot": false,
      "display_x": null,
      "display_y": null
    },
    {
      "node_id": 109,
      "x": 6450,
      "y": 4160,
      "z": null,
      "demand": 0,
      "is_depot": false,
      "display_x": null,
      "display_y": null
    },
    {
      "node_id": 110,
      "x": 6713,
      "y": 4154,
      "z": null,
      "demand": 0,
      "is_depot": false,
      "display_x": null,
      "display_y": null
    },
    {
      "node_id": 111,
      "x": 7355,
      "y": 4151,
      "z": null,
      "demand": 0,
      "is_depot": false,
      "display_x": null,
      "display_y": null
    },
    {
      "node_id": 112,
      "x": 7604,
      "y": 4146,
      "z": null,
      "demand": 0,
      "is_depot": false,
      "display_x": null,
      "display_y": null
    },
    {
      "node_id": 113,
      "x": 7541,
      "y": 4141,
      "z": null,
      "demand": 0,
      "is_depot": false,
      "display_x": null,
      "display_y": null
    },
    {
      "node_id": 114,
      "x": 7506,
      "y": 4138,
      "z": null,
      "demand": 0,
      "is_depot": false,
      "display_x": null,
      "display_y": null
    },
    {
      "node_id": 115,
      "x": 4871,
      "y": 4132,
      "z": null,
      "demand": 0,
      "is_depot": false,
      "display_x": null,
      "display_y": null
    },
    {
      "node_id": 116,
      "x": 2906,
      "y": 4131,
      "z": null,
      "demand": 0,
      "is_depot": false,
      "display_x": null,
      "display_y": null
    },
    {
      "node_id": 117,
      "x": 6488,
      "y": 4128,
      "z": null,
      "demand": 0,
      "is_depot": false,
      "display_x": null,
      "display_y": null
    },
    {
      "node_id": 118,
      "x": 6312,
      "y": 4126,
      "z": null,
      "demand": 0,
      "is_depot": false,
      "display_x": null,
      "display_y": null
    },
    {
      "node_id": 119,
      "x": 6008,
      "y": 4117,
      "z": null,
      "demand": 0,
      "is_depot": false,
      "display_x": null,
      "display_y": null
    },
    {
      "node_id": 120,
      "x": 4427,
      "y": 4109,
      "z": null,
      "demand": 0,
      "is_depot": false,
      "display_x": null,
      "display_y": null
    },
    {
      "node_id": 121,
      "x": 4679,
      "y": 4084,
      "z": null,
      "demand": 0,
      "is_depot": false,
      "display_x": null,
      "display_y": null
    },
    {
      "node_id": 122,
      "x": 5955,
      "y": 4081,
      "z": null,
      "demand": 0,
      "is_depot": false,
      "display_x": null,
      "display_y": null
    },
    {
      "node_id": 123,
      "x": 6891,
      "y": 4075,
      "z": null,
      "demand": 0,
      "is_depot": false,
      "display_x": null,
      "display_y": null
    },
    {
      "node_id": 124,
      "x": 7705,
      "y": 4065,
      "z": null,
      "demand": 0,
      "is_depot": false,
      "display_x": null,
      "display_y": null
    },
    {
      "node_id": 125,
      "x": 7562,
      "y": 4058,
      "z": null,
      "demand": 0,
      "is_depot": false,
      "display_x": null,
      "display_y": null
    },
    {
      "node_id": 126,
      "x": 4634,
      "y": 4054,
      "z": null,
      "demand": 0,
      "is_depot": false,
      "display_x": null,
      "display_y": null
    },
    {
      "node_id": 127,
      "x": 4607,
      "y": 4049,
      "z": null,
      "demand": 0,
      "is_depot": false,
      "display_x": null,
      "display_y": null
    },
    {
      "node_id": 128,
      "x": 6557,
      "y": 4047,
      "z": null,
      "demand": 0,
      "is_depot": false,
      "display_x": null,
      "display_y": null
    },
    {
      "node_id": 129,
      "x": 7344,
      "y": 4046,
      "z": null,
      "demand": 0,
      "is_depot": false,
      "display_x": null,
      "display_y": null
    },
    {
      "node_id": 130,
      "x": 5543,
      "y": 4042,
      "z": null,
      "demand": 0,
      "is_depot": false,
      "display_x": null,
      "display_y": null
    },
    {
      "node_id": 131,
      "x": 7124,
      "y": 4039,
      "z": null,
      "demand": 0,
      "is_depot": false,
      "display_x": null,
      "display_y": null
    },
    {
      "node_id": 132,
      "x": 7466,
      "y": 4037,
      "z": null,
      "demand": 0,
      "is_depot": false,
      "display_x": null,
      "display_y": null
    },
    {
      "node_id": 133,
      "x": 6259,
      "y": 4030,
      "z": null,
      "demand": 0,
      "is_depot": false,
      "display_x": null,
      "display_y": null
    },
    {
      "node_id": 134,
      "x": 6366,
      "y": 4002,
      "z": null,
      "demand": 0,
      "is_depot": false,
      "display_x": null,
      "display_y": null
    },
    {
      "node_id": 135,
      "x": 5597,
      "y": 3993,
      "z": null,
      "demand": 0,
      "is_depot": false,
      "display_x": null,
      "display_y": null
    },
    {
      "node_id": 136,
      "x": 4655,
      "y": 3992,
      "z": null,
      "demand": 0,
      "is_depot": false,
      "display_x": null,
      "display_y": null
    },
    {
      "node_id": 137,
      "x": 7805,
      "y": 3991,
      "z": null,
      "demand": 0,
      "is_depot": false,
      "display_x": null,
      "display_y": null
    },
    {
      "node_id": 138,
      "x": 3396,
      "y": 3990,
      "z": null,
      "demand": 0,
      "is_depot": false,
      "display_x": null,
      "display_y": null
    },
    {
      "node_id": 139,
      "x": 6603,
      "y": 3982,
      "z": null,
      "demand": 0,
      "is_depot": false,
      "display_x": null,
      "display_y": null
    },
    {
      "node_id": 140,
      "x": 6537,
      "y": 3982,
      "z": null,
      "demand": 0,
      "is_depot": false,
      "display_x": null,
      "display_y": null
    },
    {
      "node_id": 141,
      "x": 4342,
      "y": 3966,
      "z": null,
      "demand": 0,
      "is_depot": false,
      "display_x": null,
      "display_y": null
    },
    {
      "node_id": 142,
      "x": 7037,
      "y": 3965,
      "z": null,
      "demand": 0,
      "is_depot": false,
      "display_x": null,
      "display_y": null
    },
    {
      "node_id": 143,
      "x": 7345,
      "y": 3951,
      "z": null,
      "demand": 0,
      "is_depot": false,
      "display_x": null,
      "display_y": null
    },
    {
      "node_id": 144,
      "x": 7271,
      "y": 3948,
      "z": null,
      "demand": 0,
      "is_depot": false,
      "display_x": null,
      "display_y": null
    },
    {
      "node_id": 145,
      "x": 5336,
      "y": 3943,
      "z": null,
      "demand": 0,
      "is_depot": false,
      "display_x": null,
      "display_y": null
    },
    {
      "node_id": 146,
      "x": 5964,
      "y": 3935,
      "z": null,
      "demand": 0,
      "is_depot": false,
      "display_x": null,
      "display_y": null
    },
    {
      "node_id": 147,
      "x": 7660,
      "y": 3924,
      "z": null,
      "demand": 0,
      "is_depot": false,
      "display_x": null,
      "display_y": null
    },
    {
      "node_id": 148,
      "x": 7872,
      "y": 3922,
      "z": null,
      "demand": 0,
      "is_depot": false,
      "display_x": null,
      "display_y": null
    },
    {
      "node_id": 149,
      "x": 6567,
      "y": 3922,
      "z": null,
      "demand": 0,
      "is_depot": false,
      "display_x": null,
      "display_y": null
    },
    {
      "node_id": 150,
      "x": 6602,
      "y": 3920,
      "z": null,
      "demand": 0,
      "is_depot": false,
      "display_x": null,
      "display_y": null
    },
    {
      "node_id": 151,
      "x": 4806,
      "y": 3914,
      "z": null,
      "demand": 0,
      "is_depot": false,
      "display_x": null,
      "display_y": null
    },
    {
      "node_id": 152,
      "x": 7909,
      "y": 3912,
      "z": null,
      "demand": 0,
      "is_depot": false,
      "display_x": null,
      "display_y": null
    },
    {
      "node_id": 153,
      "x": 5926,
      "y": 3912,
      "z": null,
      "demand": 0,
      "is_depot": false,
      "display_x": null,
      "display_y": null
    },
    {
      "node_id": 154,
      "x": 7449,
      "y": 3911,
      "z": null,
      "demand": 0,
      "is_depot": false,
      "display_x": null,
      "display_y": null
    },
    {
      "node_id": 155,
      "x": 6333,
      "y": 3909,
      "z": null,
      "demand": 0,
      "is_depot": false,
      "display_x": null,
      "display_y": null
    },
    {
      "node_id": 156,
      "x": 3108,
      "y": 3908,
      "z": null,
      "demand": 0,
      "is_depot": false,
      "display_x": null,
      "display_y": null
    },
    {
      "node_id": 157,
      "x": 7844,
      "y": 3902,
      "z": null,
      "demand": 0,
      "is_depot": false,
      "display_x": null,
      "display_y": null
    },
    {
      "node_id": 158,
      "x": 5427,
      "y": 3894,
      "z": null,
      "demand": 0,
      "is_depot": false,
      "display_x": null,
      "display_y": null
    },
    {
      "node_id": 159,
      "x": 6862,
      "y": 3892,
      "z": null,
      "demand": 0,
      "is_depot": false,
      "display_x": null,
      "display_y": null
    },
    {
      "node_id": 160,
      "x": 6621,
      "y": 3891,
      "z": null,
      "demand": 0,
      "is_depot": false,
      "display_x": null,
      "display_y": null
    },
    {
      "node_id": 161,
      "x": 6150,
      "y": 3888,
      "z": null,
      "demand": 0,
      "is_depot": false,
      "display_x": null,
      "display_y": null
    },
    {
      "node_id": 162,
      "x": 7388,
      "y": 3879,
      "z": null,
      "demand": 0,
      "is_depot": false,
      "display_x": null,
      "display_y": null
    },
    {
      "node_id": 163,
      "x": 7351,
      "y": 3877,
      "z": null,
      "demand": 0,
      "is_depot": false,
      "display_x": null,
      "display_y": null
    },
    {
      "node_id": 164,
      "x": 4694,
      "y": 3877,
      "z": null,
      "demand": 0,
      "is_depot": false,
      "display_x": null,
      "display_y": null
    },
    {
      "node_id": 165,
      "x": 6340,
      "y": 3870,
      "z": null,
      "demand": 0,
      "is_depot": false,
      "display_x": null,
      "display_y": null
    },
    {
      "node_id": 166,
      "x": 6425,
      "y": 3867,
      "z": null,
      "demand": 0,
      "is_depot": false,
      "display_x": null,
      "display_y": null
    },
    {
      "node_id": 167,
      "x": 6577,
      "y": 3858,
      "z": null,
      "demand": 0,
      "is_depot": false,
      "display_x": null,
      "display_y": null
    },
    {
      "node_id": 168,
      "x": 6864,
      "y": 3854,
      "z": null,
      "demand": 0,
      "is_depot": false,
      "display_x": null,
      "display_y": null
    },
    {
      "node_id": 169,
      "x": 5706,
      "y": 3844,
      "z": null,
      "demand": 0,
      "is_depot": false,
      "display_x": null,
      "display_y": null
    },
    {
      "node_id": 170,
      "x": 4496,
      "y": 3844,
      "z": null,
      "demand": 0,
      "is_depot": false,
      "display_x": null,
      "display_y": null
    },
    {
      "node_id": 171,
      "x": 4574,
      "y": 3843,
      "z": null,
      "demand": 0,
      "is_depot": false,
      "display_x": null,
      "display_y": null
    },
    {
      "node_id": 172,
      "x": 3824,
      "y": 3838,
      "z": null,
      "demand": 0,
      "is_depot": false,
      "display_x": null,
      "display_y": null
    },
    {
      "node_id": 173,
      "x": 5803,
      "y": 3824,
      "z": null,
      "demand": 0,
      "is_depot": false,
      "display_x": null,
      "display_y": null
    },
    {
      "node_id": 174,
      "x": 5720,
      "y": 3823,
      "z": null,
      "demand": 0,
      "is_depot": false,
      "display_x": null,
      "display_y": null
    },
    {
      "node_id": 175,
      "x": 6454,
      "y": 3821,
      "z": null,
      "demand": 0,
      "is_depot": false,
      "display_x": null,
      "display_y": null
    },
    {
      "node_id": 176,
      "x": 6120,
      "y": 3821,
      "z": null,
      "demand": 0,
      "is_depot": false,
      "display_x": null,
      "display_y": null
    },
    {
      "node_id": 177,
      "x": 7988,
      "y": 3820,
      "z": null,
      "demand": 0,
      "is_depot": false,
      "display_x": null,
      "display_y": null
    },
    {
      "node_id": 178,
      "x": 6376,
      "y": 3819,
      "z": null,
      "demand": 0,
      "is_depot": false,
      "display_x": null,
      "display_y": null
    },
    {
      "node_id": 179,
      "x": 7841,
      "y": 3818,
      "z": null,
      "demand": 0,
      "is_depot": false,
      "display_x": null,
      "display_y": null
    },
    {
      "node_id": 180,
      "x": 5778,
      "y": 3813,
      "z": null,
      "demand": 0,
      "is_depot": false,
      "display_x": null,
      "display_y": null
    },
    {
      "node_id": 181,
      "x": 5457,
      "y": 3808,
      "z": null,
      "demand": 0,
      "is_depot": false,
      "display_x": null,
      "display_y": null
    },
    {
      "node_id": 182,
      "x": 5671,
      "y": 3807,
      "z": null,
      "demand": 0,
      "is_depot": false,
      "display_x": null,
      "display_y": null
    },
    {
      "node_id": 183,
      "x": 4293,
      "y": 3788,
      "z": null,
      "demand": 0,
      "is_depot": false,
      "display_x": null,
      "display_y": null
    },
    {
      "node_id": 184,
      "x": 7423,
      "y": 3776,
      "z": null,
      "demand": 0,
      "is_depot": false,
      "display_x": null,
      "display_y": null
    },
    {
      "node_id": 185,
      "x": 7342,
      "y": 3775,
      "z": null,
      "demand": 0,
      "is_depot": false,
      "display_x": null,
      "display_y": null
    },
    {
      "node_id": 186,
      "x": 5541,
      "y": 3769,
      "z": null,
      "demand": 0,
      "is_depot": false,
      "display_x": null,
      "display_y": null
    },
    {
      "node_id": 187,
      "x": 5621,
      "y": 3768,
      "z": null,
      "demand": 0,
      "is_depot": false,
      "display_x": null,
      "display_y": null
    },
    {
      "node_id": 188,
      "x": 7750,
      "y": 3760,
      "z": null,
      "demand": 0,
      "is_depot": false,
      "display_x": null,
      "display_y": null
    },
    {
      "node_id": 189,
      "x": 6327,
      "y": 3745,
      "z": null,
      "demand": 0,
      "is_depot": false,
      "display_x": null,
      "display_y": null
    },
    {
      "node_id": 190,
      "x": 7879,
      "y": 3743,
      "z": null,
      "demand": 0,
      "is_depot": false,
      "display_x": null,
      "display_y": null
    },
    {
      "node_id": 191,
      "x": 199,
      "y": 3743,
      "z": null,
      "demand": 0,
      "is_depot": false,
      "display_x": null,
      "display_y": null
    },
    {
      "node_id": 192,
      "x": 6652,
      "y": 3742,
      "z": null,
      "demand": 0,
      "is_depot": false,
      "display_x": null,
      "display_y": null
    },
    {
      "node_id": 193,
      "x": 5678,
      "y": 3742,
      "z": null,
      "demand": 0,
      "is_depot": false,
      "display_x": null,
      "display_y": null
    },
    {
      "node_id": 194,
      "x": 5207,
      "y": 3742,
      "z": null,
      "demand": 0,
      "is_depot": false,
      "display_x": null,
      "display_y": null
    },
    {
      "node_id": 195,
      "x": 7429,
      "y": 3737,
      "z": null,
      "demand": 0,
      "is_depot": false,
      "display_x": null,
      "display_y": null
    },
    {
      "node_id": 196,
      "x": 7262,
      "y": 3725,
      "z": null,
      "demand": 0,
      "is_depot": false,
      "display_x": null,
      "display_y": null
    },
    {
      "node_id": 197,
      "x": 6427,
      "y": 3717,
      "z": null,
      "demand": 0,
      "is_depot": false,
      "display_x": null,
      "display_y": null
    },
    {
      "node_id": 198,
      "x": 1851,
      "y": 3710,
      "z": null,
      "demand": 0,
      "is_depot": false,
      "display_x": null,
      "display_y": null
    },
    {
      "node_id": 199,
      "x": 6207,
      "y": 3700,
      "z": null,
      "demand": 0,
      "is_depot": false,
      "display_x": null,
      "display_y": null
    },
    {
      "node_id": 200,
      "x": 6069,
      "y": 3695,
      "z": null,
      "demand": 0,
      "is_depot": false,
      "display_x": null,
      "display_y": null
    },
    {
      "node_id": 201,
      "x": 4780,
      "y": 3694,
      "z": null,
      "demand": 0,
      "is_depot": false,
      "display_x": null,
      "display_y": null
    },
    {
      "node_id": 202,
      "x": 7603,
      "y": 3690,
      "z": null,
      "demand": 0,
      "is_depot": false,
      "display_x": null,
      "display_y": null
    },
    {
      "node_id": 203,
      "x": 5751,
      "y": 3681,
      "z": null,
      "demand": 0,
      "is_depot": false,
      "display_x": null,
      "display_y": null
    },
    {
      "node_id": 204,
      "x": 6365,
      "y": 3679,
      "z": null,
      "demand": 0,
      "is_depot": false,
      "display_x": null,
      "display_y": null
    },
    {
      "node_id": 205,
      "x": 6958,
      "y": 3678,
      "z": null,
      "demand": 0,
      "is_depot": false,
      "display_x": null,
      "display_y": null
    },
    {
      "node_id": 206,
      "x": 6317,
      "y": 3673,
      "z": null,
      "demand": 0,
      "is_depot": false,
      "display_x": null,
      "display_y": null
    },
    {
      "node_id": 207,
      "x": 5417,
      "y": 3673,
      "z": null,
      "demand": 0,
      "is_depot": false,
      "display_x": null,
      "display_y": null
    },
    {
      "node_id": 208,
      "x": 6426,
      "y": 3656,
      "z": null,
      "demand": 0,
      "is_depot": false,
      "display_x": null,
      "display_y": null
    },
    {
      "node_id": 209,
      "x": 7922,
      "y": 3655,
      "z": null,
      "demand": 0,
      "is_depot": false,
      "display_x": null,
      "display_y": null
    },
    {
      "node_id": 210,
      "x": 7331,
      "y": 3634,
      "z": null,
      "demand": 0,
      "is_depot": false,
      "display_x": null,
      "display_y": null
    },
    {
      "node_id": 211,
      "x": 5965,
      "y": 3624,
      "z": null,
      "demand": 0,
      "is_depot": false,
      "display_x": null,
      "display_y": null
    },
    {
      "node_id": 212,
      "x": 4965,
      "y": 3622,
      "z": null,
      "demand": 0,
      "is_depot": false,
      "display_x": null,
      "display_y": null
    },
    {
      "node_id": 213,
      "x": 6833,
      "y": 3618,
      "z": null,
      "demand": 0,
      "is_depot": false,
      "display_x": null,
      "display_y": null
    },
    {
      "node_id": 214,
      "x": 6798,
      "y": 3610,
      "z": null,
      "demand": 0,
      "is_depot": false,
      "display_x": null,
      "display_y": null
    },
    {
      "node_id": 215,
      "x": 7667,
      "y": 3608,
      "z": null,
      "demand": 0,
      "is_depot": false,
      "display_x": null,
      "display_y": null
    },
    {
      "node_id": 216,
      "x": 1047,
      "y": 3602,
      "z": null,
      "demand": 0,
      "is_depot": false,
      "display_x": null,
      "display_y": null
    },
    {
      "node_id": 217,
      "x": 7803,
      "y": 3598,
      "z": null,
      "demand": 0,
      "is_depot": false,
      "display_x": null,
      "display_y": null
    },
    {
      "node_id": 218,
      "x": 7370,
      "y": 3588,
      "z": null,
      "demand": 0,
      "is_depot": false,
      "display_x": null,
      "display_y": null
    },
    {
      "node_id": 219,
      "x": 952,
      "y": 3583,
      "z": null,
      "demand": 0,
      "is_depot": false,
      "display_x": null,
      "display_y": null
    },
    {
      "node_id": 220,
      "x": 7906,
      "y": 3580,
      "z": null,
      "demand": 0,
      "is_depot": false,
      "display_x": null,
      "display_y": null
    },
    {
      "node_id": 221,
      "x": 250,
      "y": 3578,
      "z": null,
      "demand": 0,
      "is_depot": false,
      "display_x": null,
      "display_y": null
    },
    {
      "node_id": 222,
      "x": 5111,
      "y": 3569,
      "z": null,
      "demand": 0,
      "is_depot": false,
      "display_x": null,
      "display_y": null
    },
    {
      "node_id": 223,
      "x": 6453,
      "y": 3567,
      "z": null,
      "demand": 0,
      "is_depot": false,
      "display_x": null,
      "display_y": null
    },
    {
      "node_id": 224,
      "x": 7492,
      "y": 3560,
      "z": null,
      "demand": 0,
      "is_depot": false,
      "display_x": null,
      "display_y": null
    },
    {
      "node_id": 225,
      "x": 6140,
      "y": 3558,
      "z": null,
      "demand": 0,
      "is_depot": false,
      "display_x": null,
      "display_y": null
    },
    {
      "node_id": 226,
      "x": 5315,
      "y": 3557,
      "z": null,
      "demand": 0,
      "is_depot": false,
      "display_x": null,
      "display_y": null
    },
    {
      "node_id": 227,
      "x": 5316,
      "y": 3554,
      "z": null,
      "demand": 0,
      "is_depot": false,
      "display_x": null,
      "display_y": null
    },
    {
      "node_id": 228,
      "x": 4232,
      "y": 3551,
      "z": null,
      "demand": 0,
      "is_depot": false,
      "display_x": null,
      "display_y": null
    },
    {
      "node_id": 229,
      "x": 7408,
      "y": 3534,
      "z": null,
      "demand": 0,
      "is_depot": false,
      "display_x": null,
      "display_y": null
    },
    {
      "node_id": 230,
      "x": 8013,
      "y": 3523,
      "z": null,
      "demand": 0,
      "is_depot": false,
      "display_x": null,
      "display_y": null
    },
    {
      "node_id": 231,
      "x": 5160,
      "y": 3517,
      "z": null,
      "demand": 0,
      "is_depot": false,
      "display_x": null,
      "display_y": null
    },
    {
      "node_id": 232,
      "x": 7141,
      "y": 3514,
      "z": null,
      "demand": 0,
      "is_depot": false,
      "display_x": null,
      "display_y": null
    },
    {
      "node_id": 233,
      "x": 5887,
      "y": 3508,
      "z": null,
      "demand": 0,
      "is_depot": false,
      "display_x": null,
      "display_y": null
    },
    {
      "node_id": 234,
      "x": 4694,
      "y": 3502,
      "z": null,
      "demand": 0,
      "is_depot": false,
      "display_x": null,
      "display_y": null
    },
    {
      "node_id": 235,
      "x": 7633,
      "y": 3499,
      "z": null,
      "demand": 0,
      "is_depot": false,
      "display_x": null,
      "display_y": null
    },
    {
      "node_id": 236,
      "x": 7919,
      "y": 3496,
      "z": null,
      "demand": 0,
      "is_depot": false,
      "display_x": null,
      "display_y": null
    },
    {
      "node_id": 237,
      "x": 1784,
      "y": 3494,
      "z": null,
      "demand": 0,
      "is_depot": false,
      "display_x": null,
      "display_y": null
    },
    {
      "node_id": 238,
      "x": 1482,
      "y": 3494,
      "z": null,
      "demand": 0,
      "is_depot": false,
      "display_x": null,
      "display_y": null
    },
    {
      "node_id": 239,
      "x": 236,
      "y": 3494,
      "z": null,
      "demand": 0,
      "is_depot": false,
      "display_x": null,
      "display_y": null
    },
    {
      "node_id": 240,
      "x": 6713,
      "y": 3488,
      "z": null,
      "demand": 0,
      "is_depot": false,
      "display_x": null,
      "display_y": null
    },
    {
      "node_id": 241,
      "x": 7696,
      "y": 3486,
      "z": null,
      "demand": 0,
      "is_depot": false,
      "display_x": null,
      "display_y": null
    },
    {
      "node_id": 242,
      "x": 536,
      "y": 3481,
      "z": null,
      "demand": 0,
      "is_depot": false,
      "display_x": null,
      "display_y": null
    },
    {
      "node_id": 243,
      "x": 317,
      "y": 3476,
      "z": null,
      "demand": 0,
      "is_depot": false,
      "display_x": null,
      "display_y": null
    },
    {
      "node_id": 244,
      "x": 5649,
      "y": 3472,
      "z": null,
      "demand": 0,
      "is_depot": false,
      "display_x": null,
      "display_y": null
    },
    {
      "node_id": 245,
      "x": 6235,
      "y": 3471,
      "z": null,
      "demand": 0,
      "is_depot": false,
      "display_x": null,
      "display_y": null
    },
    {
      "node_id": 246,
      "x": 7199,
      "y": 3469,
      "z": null,
      "demand": 0,
      "is_depot": false,
      "display_x": null,
      "display_y": null
    },
    {
      "node_id": 247,
      "x": 5540,
      "y": 3468,
      "z": null,
      "demand": 0,
      "is_depot": false,
      "display_x": null,
      "display_y": null
    },
    {
      "node_id": 248,
      "x": 5400,
      "y": 3461,
      "z": null,
      "demand": 0,
      "is_depot": false,
      "display_x": null,
      "display_y": null
    },
    {
      "node_id": 249,
      "x": 5796,
      "y": 3459,
      "z": null,
      "demand": 0,
      "is_depot": false,
      "display_x": null,
      "display_y": null
    },
    {
      "node_id": 250,
      "x": 2342,
      "y": 3439,
      "z": null,
      "demand": 0,
      "is_depot": false,
      "display_x": null,
      "display_y": null
    },
    {
      "node_id": 251,
      "x": 7494,
      "y": 3430,
      "z": null,
      "demand": 0,
      "is_depot": false,
      "display_x": null,
      "display_y": null
    },
    {
      "node_id": 252,
      "x": 7321,
      "y": 3429,
      "z": null,
      "demand": 0,
      "is_depot": false,
      "display_x": null,
      "display_y": null
    },
    {
      "node_id": 253,
      "x": 6265,
      "y": 3426,
      "z": null,
      "demand": 0,
      "is_depot": false,
      "display_x": null,
      "display_y": null
    },
    {
      "node_id": 254,
      "x": 8001,
      "y": 3418,
      "z": null,
      "demand": 0,
      "is_depot": false,
      "display_x": null,
      "display_y": null
    },
    {
      "node_id": 255,
      "x": 226,
      "y": 3415,
      "z": null,
      "demand": 0,
      "is_depot": false,
      "display_x": null,
      "display_y": null
    },
    {
      "node_id": 256,
      "x": 6148,
      "y": 3413,
      "z": null,
      "demand": 0,
      "is_depot": false,
      "display_x": null,
      "display_y": null
    },
    {
      "node_id": 257,
      "x": 5987,
      "y": 3402,
      "z": null,
      "demand": 0,
      "is_depot": false,
      "display_x": null,
      "display_y": null
    },
    {
      "node_id": 258,
      "x": 7582,
      "y": 3396,
      "z": null,
      "demand": 0,
      "is_depot": false,
      "display_x": null,
      "display_y": null
    },
    {
      "node_id": 259,
      "x": 7422,
      "y": 3390,
      "z": null,
      "demand": 0,
      "is_depot": false,
      "display_x": null,
      "display_y": null
    },
    {
      "node_id": 260,
      "x": 6623,
      "y": 3389,
      "z": null,
      "demand": 0,
      "is_depot": false,
      "display_x": null,
      "display_y": null
    },
    {
      "node_id": 261,
      "x": 7475,
      "y": 3388,
      "z": null,
      "demand": 0,
      "is_depot": false,
      "display_x": null,
      "display_y": null
    },
    {
      "node_id": 262,
      "x": 7654,
      "y": 3377,
      "z": null,
      "demand": 0,
      "is_depot": false,
      "display_x": null,
      "display_y": null
    },
    {
      "node_id": 263,
      "x": 7838,
      "y": 3375,
      "z": null,
      "demand": 0,
      "is_depot": false,
      "display_x": null,
      "display_y": null
    },
    {
      "node_id": 264,
      "x": 6570,
      "y": 3371,
      "z": null,
      "demand": 0,
      "is_depot": false,
      "display_x": null,
      "display_y": null
    },
    {
      "node_id": 265,
      "x": 4364,
      "y": 3362,
      "z": null,
      "demand": 0,
      "is_depot": false,
      "display_x": null,
      "display_y": null
    },
    {
      "node_id": 266,
      "x": 7316,
      "y": 3360,
      "z": null,
      "demand": 0,
      "is_depot": false,
      "display_x": null,
      "display_y": null
    },
    {
      "node_id": 267,
      "x": 4857,
      "y": 3359,
      "z": null,
      "demand": 0,
      "is_depot": false,
      "display_x": null,
      "display_y": null
    },
    {
      "node_id": 268,
      "x": 7533,
      "y": 3358,
      "z": null,
      "demand": 0,
      "is_depot": false,
      "display_x": null,
      "display_y": null
    },
    {
      "node_id": 269,
      "x": 5719,
      "y": 3352,
      "z": null,
      "demand": 0,
      "is_depot": false,
      "display_x": null,
      "display_y": null
    },
    {
      "node_id": 270,
      "x": 7452,
      "y": 3339,
      "z": null,
      "demand": 0,
      "is_depot": false,
      "display_x": null,
      "display_y": null
    },
    {
      "node_id": 271,
      "x": 7747,
      "y": 3329,
      "z": null,
      "demand": 0,
      "is_depot": false,
      "display_x": null,
      "display_y": null
    },
    {
      "node_id": 272,
      "x": 5841,
      "y": 3328,
      "z": null,
      "demand": 0,
      "is_depot": false,
      "display_x": null,
      "display_y": null
    },
    {
      "node_id": 273,
      "x": 3229,
      "y": 3312,
      "z": null,
      "demand": 0,
      "is_depot": false,
      "display_x": null,
      "display_y": null
    },
    {
      "node_id": 274,
      "x": 7076,
      "y": 3302,
      "z": null,
      "demand": 0,
      "is_depot": false,
      "display_x": null,
      "display_y": null
    },
    {
      "node_id": 275,
      "x": 7657,
      "y": 3301,
      "z": null,
      "demand": 0,
      "is_depot": false,
      "display_x": null,
      "display_y": null
    },
    {
      "node_id": 276,
      "x": 6360,
      "y": 3301,
      "z": null,
      "demand": 0,
      "is_depot": false,
      "display_x": null,
      "display_y": null
    },
    {
      "node_id": 277,
      "x": 525,
      "y": 3297,
      "z": null,
      "demand": 0,
      "is_depot": false,
      "display_x": null,
      "display_y": null
    },
    {
      "node_id": 278,
      "x": 5619,
      "y": 3291,
      "z": null,
      "demand": 0,
      "is_depot": false,
      "display_x": null,
      "display_y": null
    },
    {
      "node_id": 279,
      "x": 7989,
      "y": 3271,
      "z": null,
      "demand": 0,
      "is_depot": false,
      "display_x": null,
      "display_y": null
    },
    {
      "node_id": 280,
      "x": 5697,
      "y": 3269,
      "z": null,
      "demand": 0,
      "is_depot": false,
      "display_x": null,
      "display_y": null
    },
    {
      "node_id": 281,
      "x": 6050,
      "y": 3242,
      "z": null,
      "demand": 0,
      "is_depot": false,
      "display_x": null,
      "display_y": null
    },
    {
      "node_id": 282,
      "x": 7082,
      "y": 3235,
      "z": null,
      "demand": 0,
      "is_depot": false,
      "display_x": null,
      "display_y": null
    },
    {
      "node_id": 283,
      "x": 5539,
      "y": 3235,
      "z": null,
      "demand": 0,
      "is_depot": false,
      "display_x": null,
      "display_y": null
    },
    {
      "node_id": 284,
      "x": 741,
      "y": 3235,
      "z": null,
      "demand": 0,
      "is_depot": false,
      "display_x": null,
      "display_y": null
    },
    {
      "node_id": 285,
      "x": 6731,
      "y": 3234,
      "z": null,
      "demand": 0,
      "is_depot": false,
      "display_x": null,
      "display_y": null
    },
    {
      "node_id": 286,
      "x": 7453,
      "y": 3229,
      "z": null,
      "demand": 0,
      "is_depot": false,
      "display_x": null,
      "display_y": null
    },
    {
      "node_id": 287,
      "x": 7695,
      "y": 3220,
      "z": null,
      "demand": 0,
      "is_depot": false,
      "display_x": null,
      "display_y": null
    },
    {
      "node_id": 288,
      "x": 7299,
      "y": 3219,
      "z": null,
      "demand": 0,
      "is_depot": false,
      "display_x": null,
      "display_y": null
    },
    {
      "node_id": 289,
      "x": 863,
      "y": 3219,
      "z": null,
      "demand": 0,
      "is_depot": false,
      "display_x": null,
      "display_y": null
    },
    {
      "node_id": 290,
      "x": 7861,
      "y": 3216,
      "z": null,
      "demand": 0,
      "is_depot": false,
      "display_x": null,
      "display_y": null
    },
    {
      "node_id": 291,
      "x": 5960,
      "y": 3207,
      "z": null,
      "demand": 0,
      "is_depot": false,
      "display_x": null,
      "display_y": null
    },
    {
      "node_id": 292,
      "x": 4252,
      "y": 3206,
      "z": null,
      "demand": 0,
      "is_depot": false,
      "display_x": null,
      "display_y": null
    },
    {
      "node_id": 293,
      "x": 6402,
      "y": 3190,
      "z": null,
      "demand": 0,
      "is_depot": false,
      "display_x": null,
      "display_y": null
    },
    {
      "node_id": 294,
      "x": 5342,
      "y": 3188,
      "z": null,
      "demand": 0,
      "is_depot": false,
      "display_x": null,
      "display_y": null
    },
    {
      "node_id": 295,
      "x": 6656,
      "y": 3181,
      "z": null,
      "demand": 0,
      "is_depot": false,
      "display_x": null,
      "display_y": null
    },
    {
      "node_id": 296,
      "x": 7532,
      "y": 3175,
      "z": null,
      "demand": 0,
      "is_depot": false,
      "display_x": null,
      "display_y": null
    },
    {
      "node_id": 297,
      "x": 7434,
      "y": 3173,
      "z": null,
      "demand": 0,
      "is_depot": false,
      "display_x": null,
      "display_y": null
    },
    {
      "node_id": 298,
      "x": 5679,
      "y": 3171,
      "z": null,
      "demand": 0,
      "is_depot": false,
      "display_x": null,
      "display_y": null
    },
    {
      "node_id": 299,
      "x": 6518,
      "y": 3165,
      "z": null,
      "demand": 0,
      "is_depot": false,
      "display_x": null,
      "display_y": null
    },
    {
      "node_id": 300,
      "x": 4537,
      "y": 3143,
      "z": null,
      "demand": 0,
      "is_depot": false,
      "display_x": null,
      "display_y": null
    },
    {
      "node_id": 301,
      "x": 806,
      "y": 3123,
      "z": null,
      "demand": 0,
      "is_depot": false,
      "display_x": null,
      "display_y": null
    },
    {
      "node_id": 302,
      "x": 6113,
      "y": 3101,
      "z": null,
      "demand": 0,
      "is_depot": false,
      "display_x": null,
      "display_y": null
    },
    {
      "node_id": 303,
      "x": 7440,
      "y": 3100,
      "z": null,
      "demand": 0,
      "is_depot": false,
      "display_x": null,
      "display_y": null
    },
    {
      "node_id": 304,
      "x": 6204,
      "y": 3099,
      "z": null,
      "demand": 0,
      "is_depot": false,
      "display_x": null,
      "display_y": null
    },
    {
      "node_id": 305,
      "x": 7715,
      "y": 3086,
      "z": null,
      "demand": 0,
      "is_depot": false,
      "display_x": null,
      "display_y": null
    },
    {
      "node_id": 306,
      "x": 7503,
      "y": 3086,
      "z": null,
      "demand": 0,
      "is_depot": false,
      "display_x": null,
      "display_y": null
    },
    {
      "node_id": 307,
      "x": 5821,
      "y": 3086,
      "z": null,
      "demand": 0,
      "is_depot": false,
      "display_x": null,
      "display_y": null
    },
    {
      "node_id": 308,
      "x": 7131,
      "y": 3081,
      "z": null,
      "demand": 0,
      "is_depot": false,
      "display_x": null,
      "display_y": null
    },
    {
      "node_id": 309,
      "x": 7909,
      "y": 3080,
      "z": null,
      "demand": 0,
      "is_depot": false,
      "display_x": null,
      "display_y": null
    },
    {
      "node_id": 310,
      "x": 920,
      "y": 3065,
      "z": null,
      "demand": 0,
      "is_depot": false,
      "display_x": null,
      "display_y": null
    },
    {
      "node_id": 311,
      "x": 6468,
      "y": 3050,
      "z": null,
      "demand": 0,
      "is_depot": false,
      "display_x": null,
      "display_y": null
    },
    {
      "node_id": 312,
      "x": 5677,
      "y": 3049,
      "z": null,
      "demand": 0,
      "is_depot": false,
      "display_x": null,
      "display_y": null
    },
    {
      "node_id": 313,
      "x": 218,
      "y": 3031,
      "z": null,
      "demand": 0,
      "is_depot": false,
      "display_x": null,
      "display_y": null
    },
    {
      "node_id": 314,
      "x": 6881,
      "y": 3029,
      "z": null,
      "demand": 0,
      "is_depot": false,
      "display_x": null,
      "display_y": null
    },
    {
      "node_id": 315,
      "x": 5650,
      "y": 3023,
      "z": null,
      "demand": 0,
      "is_depot": false,
      "display_x": null,
      "display_y": null
    },
    {
      "node_id": 316,
      "x": 197,
      "y": 3021,
      "z": null,
      "demand": 0,
      "is_depot": false,
      "display_x": null,
      "display_y": null
    },
    {
      "node_id": 317,
      "x": 5531,
      "y": 3011,
      "z": null,
      "demand": 0,
      "is_depot": false,
      "display_x": null,
      "display_y": null
    },
    {
      "node_id": 318,
      "x": 6387,
      "y": 3008,
      "z": null,
      "demand": 0,
      "is_depot": false,
      "display_x": null,
      "display_y": null
    },
    {
      "node_id": 319,
      "x": 4458,
      "y": 3007,
      "z": null,
      "demand": 0,
      "is_depot": false,
      "display_x": null,
      "display_y": null
    },
    {
      "node_id": 320,
      "x": 6190,
      "y": 2985,
      "z": null,
      "demand": 0,
      "is_depot": false,
      "display_x": null,
      "display_y": null
    },
    {
      "node_id": 321,
      "x": 7055,
      "y": 2981,
      "z": null,
      "demand": 0,
      "is_depot": false,
      "display_x": null,
      "display_y": null
    },
    {
      "node_id": 322,
      "x": 7238,
      "y": 2957,
      "z": null,
      "demand": 0,
      "is_depot": false,
      "display_x": null,
      "display_y": null
    },
    {
      "node_id": 323,
      "x": 5930,
      "y": 2948,
      "z": null,
      "demand": 0,
      "is_depot": false,
      "display_x": null,
      "display_y": null
    },
    {
      "node_id": 324,
      "x": 7543,
      "y": 2929,
      "z": null,
      "demand": 0,
      "is_depot": false,
      "display_x": null,
      "display_y": null
    },
    {
      "node_id": 325,
      "x": 5291,
      "y": 2929,
      "z": null,
      "demand": 0,
      "is_depot": false,
      "display_x": null,
      "display_y": null
    },
    {
      "node_id": 326,
      "x": 4196,
      "y": 2929,
      "z": null,
      "demand": 0,
      "is_depot": false,
      "display_x": null,
      "display_y": null
    },
    {
      "node_id": 327,
      "x": 6617,
      "y": 2928,
      "z": null,
      "demand": 0,
      "is_depot": false,
      "display_x": null,
      "display_y": null
    },
    {
      "node_id": 328,
      "x": 4831,
      "y": 2917,
      "z": null,
      "demand": 0,
      "is_depot": false,
      "display_x": null,
      "display_y": null
    },
    {
      "node_id": 329,
      "x": 2835,
      "y": 2912,
      "z": null,
      "demand": 0,
      "is_depot": false,
      "display_x": null,
      "display_y": null
    },
    {
      "node_id": 330,
      "x": 174,
      "y": 2901,
      "z": null,
      "demand": 0,
      "is_depot": false,
      "display_x": null,
      "display_y": null
    },
    {
      "node_id": 331,
      "x": 5350,
      "y": 2867,
      "z": null,
      "demand": 0,
      "is_depot": false,
      "display_x": null,
      "display_y": null
    },
    {
      "node_id": 332,
      "x": 7346,
      "y": 2858,
      "z": null,
      "demand": 0,
      "is_depot": false,
      "display_x": null,
      "display_y": null
    },
    {
      "node_id": 333,
      "x": 6044,
      "y": 2848,
      "z": null,
      "demand": 0,
      "is_depot": false,
      "display_x": null,
      "display_y": null
    },
    {
      "node_id": 334,
      "x": 4898,
      "y": 2840,
      "z": null,
      "demand": 0,
      "is_depot": false,
      "display_x": null,
      "display_y": null
    },
    {
      "node_id": 335,
      "x": 3307,
      "y": 2833,
      "z": null,
      "demand": 0,
      "is_depot": false,
      "display_x": null,
      "display_y": null
    },
    {
      "node_id": 336,
      "x": 1918,
      "y": 2832,
      "z": null,
      "demand": 0,
      "is_depot": false,
      "display_x": null,
      "display_y": null
    },
    {
      "node_id": 337,
      "x": 7125,
      "y": 2823,
      "z": null,
      "demand": 0,
      "is_depot": false,
      "display_x": null,
      "display_y": null
    },
    {
      "node_id": 338,
      "x": 6422,
      "y": 2820,
      "z": null,
      "demand": 0,
      "is_depot": false,
      "display_x": null,
      "display_y": null
    },
    {
      "node_id": 339,
      "x": 5881,
      "y": 2817,
      "z": null,
      "demand": 0,
      "is_depot": false,
      "display_x": null,
      "display_y": null
    },
    {
      "node_id": 340,
      "x": 141,
      "y": 2814,
      "z": null,
      "demand": 0,
      "is_depot": false,
      "display_x": null,
      "display_y": null
    },
    {
      "node_id": 341,
      "x": 7851,
      "y": 2809,
      "z": null,
      "demand": 0,
      "is_depot": false,
      "display_x": null,
      "display_y": null
    },
    {
      "node_id": 342,
      "x": 4929,
      "y": 2803,
      "z": null,
      "demand": 0,
      "is_depot": false,
      "display_x": null,
      "display_y": null
    },
    {
      "node_id": 343,
      "x": 5963,
      "y": 2789,
      "z": null,
      "demand": 0,
      "is_depot": false,
      "display_x": null,
      "display_y": null
    },
    {
      "node_id": 344,
      "x": 5470,
      "y": 2774,
      "z": null,
      "demand": 0,
      "is_depot": false,
      "display_x": null,
      "display_y": null
    },
    {
      "node_id": 345,
      "x": 7458,
      "y": 2741,
      "z": null,
      "demand": 0,
      "is_depot": false,
      "display_x": null,
      "display_y": null
    },
    {
      "node_id": 346,
      "x": 1263,
      "y": 2734,
      "z": null,
      "demand": 0,
      "is_depot": false,
      "display_x": null,
      "display_y": null
    },
    {
      "node_id": 347,
      "x": 6766,
      "y": 2732,
      "z": null,
      "demand": 0,
      "is_depot": false,
      "display_x": null,
      "display_y": null
    },
    {
      "node_id": 348,
      "x": 4763,
      "y": 2720,
      "z": null,
      "demand": 0,
      "is_depot": false,
      "display_x": null,
      "display_y": null
    },
    {
      "node_id": 349,
      "x": 3461,
      "y": 2718,
      "z": null,
      "demand": 0,
      "is_depot": false,
      "display_x": null,
      "display_y": null
    },
    {
      "node_id": 350,
      "x": 7309,
      "y": 2717,
      "z": null,
      "demand": 0,
      "is_depot": false,
      "display_x": null,
      "display_y": null
    },
    {
      "node_id": 351,
      "x": 6848,
      "y": 2712,
      "z": null,
      "demand": 0,
      "is_depot": false,
      "display_x": null,
      "display_y": null
    },
    {
      "node_id": 352,
      "x": 178,
      "y": 2702,
      "z": null,
      "demand": 0,
      "is_depot": false,
      "display_x": null,
      "display_y": null
    },
    {
      "node_id": 353,
      "x": 1882,
      "y": 2684,
      "z": null,
      "demand": 0,
      "is_depot": false,
      "display_x": null,
      "display_y": null
    },
    {
      "node_id": 354,
      "x": 4584,
      "y": 2643,
      "z": null,
      "demand": 0,
      "is_depot": false,
      "display_x": null,
      "display_y": null
    },
    {
      "node_id": 355,
      "x": 3174,
      "y": 2627,
      "z": null,
      "demand": 0,
      "is_depot": false,
      "display_x": null,
      "display_y": null
    },
    {
      "node_id": 356,
      "x": 7049,
      "y": 2570,
      "z": null,
      "demand": 0,
      "is_depot": false,
      "display_x": null,
      "display_y": null
    },
    {
      "node_id": 357,
      "x": 7753,
      "y": 2564,
      "z": null,
      "demand": 0,
      "is_depot": false,
      "display_x": null,
      "display_y": null
    },
    {
      "node_id": 358,
      "x": 6597,
      "y": 2563,
      "z": null,
      "demand": 0,
      "is_depot": false,
      "display_x": null,
      "display_y": null
    },
    {
      "node_id": 359,
      "x": 4476,
      "y": 2555,
      "z": null,
      "demand": 0,
      "is_depot": false,
      "display_x": null,
      "display_y": null
    },
    {
      "node_id": 360,
      "x": 1575,
      "y": 2555,
      "z": null,
      "demand": 0,
      "is_depot": false,
      "display_x": null,
      "display_y": null
    },
    {
      "node_id": 361,
      "x": 7304,
      "y": 2550,
      "z": null,
      "demand": 0,
      "is_depot": false,
      "display_x": null,
      "display_y": null
    },
    {
      "node_id": 362,
      "x": 10,
      "y": 2537,
      "z": null,
      "demand": 0,
      "is_depot": false,
      "display_x": null,
      "display_y": null
    },
    {
      "node_id": 363,
      "x": 6800,
      "y": 2532,
      "z": null,
      "demand": 0,
      "is_depot": false,
      "display_x": null,
      "display_y": null
    },
    {
      "node_id": 364,
      "x": 5296,
      "y": 2520,
      "z": null,
      "demand": 0,
      "is_depot": false,
      "display_x": null,
      "display_y": null
    },
    {
      "node_id": 365,
      "x": 7104,
      "y": 2510,
      "z": null,
      "demand": 0,
      "is_depot": false,
      "display_x": null,
      "display_y": null
    },
    {
      "node_id": 366,
      "x": 6547,
      "y": 2506,
      "z": null,
      "demand": 0,
      "is_depot": false,
      "display_x": null,
      "display_y": null
    },
    {
      "node_id": 367,
      "x": 7267,
      "y": 2466,
      "z": null,
      "demand": 0,
      "is_depot": false,
      "display_x": null,
      "display_y": null
    },
    {
      "node_id": 368,
      "x": 3189,
      "y": 2411,
      "z": null,
      "demand": 0,
      "is_depot": false,
      "display_x": null,
      "display_y": null
    },
    {
      "node_id": 369,
      "x": 5117,
      "y": 2409,
      "z": null,
      "demand": 0,
      "is_depot": false,
      "display_x": null,
      "display_y": null
    },
    {
      "node_id": 370,
      "x": 4973,
      "y": 2406,
      "z": null,
      "demand": 0,
      "is_depot": false,
      "display_x": null,
      "display_y": null
    },
    {
      "node_id": 371,
      "x": 4488,
      "y": 2378,
      "z": null,
      "demand": 0,
      "is_depot": false,
      "display_x": null,
      "display_y": null
    },
    {
      "node_id": 372,
      "x": 7351,
      "y": 2376,
      "z": null,
      "demand": 0,
      "is_depot": false,
      "display_x": null,
      "display_y": null
    },
    {
      "node_id": 373,
      "x": 6007,
      "y": 2359,
      "z": null,
      "demand": 0,
      "is_depot": false,
      "display_x": null,
      "display_y": null
    },
    {
      "node_id": 374,
      "x": 4612,
      "y": 2341,
      "z": null,
      "demand": 0,
      "is_depot": false,
      "display_x": null,
      "display_y": null
    },
    {
      "node_id": 375,
      "x": 7015,
      "y": 2333,
      "z": null,
      "demand": 0,
      "is_depot": false,
      "display_x": null,
      "display_y": null
    },
    {
      "node_id": 376,
      "x": 3233,
      "y": 2329,
      "z": null,
      "demand": 0,
      "is_depot": false,
      "display_x": null,
      "display_y": null
    },
    {
      "node_id": 377,
      "x": 240,
      "y": 2327,
      "z": null,
      "demand": 0,
      "is_depot": false,
      "display_x": null,
      "display_y": null
    },
    {
      "node_id": 378,
      "x": 6686,
      "y": 2312,
      "z": null,
      "demand": 0,
      "is_depot": false,
      "display_x": null,
      "display_y": null
    },
    {
      "node_id": 379,
      "x": 6307,
      "y": 2295,
      "z": null,
      "demand": 0,
      "is_depot": false,
      "display_x": null,
      "display_y": null
    },
    {
      "node_id": 380,
      "x": 7448,
      "y": 2291,
      "z": null,
      "demand": 0,
      "is_depot": false,
      "display_x": null,
      "display_y": null
    },
    {
      "node_id": 381,
      "x": 7087,
      "y": 2274,
      "z": null,
      "demand": 0,
      "is_depot": false,
      "display_x": null,
      "display_y": null
    },
    {
      "node_id": 382,
      "x": 2067,
      "y": 2254,
      "z": null,
      "demand": 0,
      "is_depot": false,
      "display_x": null,
      "display_y": null
    },
    {
      "node_id": 383,
      "x": 5260,
      "y": 2230,
      "z": null,
      "demand": 0,
      "is_depot": false,
      "display_x": null,
      "display_y": null
    },
    {
      "node_id": 384,
      "x": 4174,
      "y": 2190,
      "z": null,
      "demand": 0,
      "is_depot": false,
      "display_x": null,
      "display_y": null
    },
    {
      "node_id": 385,
      "x": 36,
      "y": 2185,
      "z": null,
      "demand": 0,
      "is_depot": false,
      "display_x": null,
      "display_y": null
    },
    {
      "node_id": 386,
      "x": 7856,
      "y": 2181,
      "z": null,
      "demand": 0,
      "is_depot": false,
      "display_x": null,
      "display_y": null
    },
    {
      "node_id": 387,
      "x": 7315,
      "y": 2181,
      "z": null,
      "demand": 0,
      "is_depot": false,
      "display_x": null,
      "display_y": null
    },
    {
      "node_id": 388,
      "x": 3319,
      "y": 2151,
      "z": null,
      "demand": 0,
      "is_depot": false,
      "display_x": null,
      "display_y": null
    },
    {
      "node_id": 389,
      "x": 2126,
      "y": 2150,
      "z": null,
      "demand": 0,
      "is_depot": false,
      "display_x": null,
      "display_y": null
    },
    {
      "node_id": 390,
      "x": 7418,
      "y": 2139,
      "z": null,
      "demand": 0,
      "is_depot": false,
      "display_x": null,
      "display_y": null
    },
    {
      "node_id": 391,
      "x": 6885,
      "y": 2138,
      "z": null,
      "demand": 0,
      "is_depot": false,
      "display_x": null,
      "display_y": null
    },
    {
      "node_id": 392,
      "x": 4959,
      "y": 2123,
      "z": null,
      "demand": 0,
      "is_depot": false,
      "display_x": null,
      "display_y": null
    },
    {
      "node_id": 393,
      "x": 4996,
      "y": 2115,
      "z": null,
      "demand": 0,
      "is_depot": false,
      "display_x": null,
      "display_y": null
    },
    {
      "node_id": 394,
      "x": 5681,
      "y": 2109,
      "z": null,
      "demand": 0,
      "is_depot": false,
      "display_x": null,
      "display_y": null
    },
    {
      "node_id": 395,
      "x": 5277,
      "y": 2078,
      "z": null,
      "demand": 0,
      "is_depot": false,
      "display_x": null,
      "display_y": null
    },
    {
      "node_id": 396,
      "x": 7643,
      "y": 2048,
      "z": null,
      "demand": 0,
      "is_depot": false,
      "display_x": null,
      "display_y": null
    },
    {
      "node_id": 397,
      "x": 3390,
      "y": 2043,
      "z": null,
      "demand": 0,
      "is_depot": false,
      "display_x": null,
      "display_y": null
    },
    {
      "node_id": 398,
      "x": 8080,
      "y": 2039,
      "z": null,
      "demand": 0,
      "is_depot": false,
      "display_x": null,
      "display_y": null
    },
    {
      "node_id": 399,
      "x": 6139,
      "y": 2032,
      "z": null,
      "demand": 0,
      "is_depot": false,
      "display_x": null,
      "display_y": null
    },
    {
      "node_id": 400,
      "x": 2694,
      "y": 2026,
      "z": null,
      "demand": 0,
      "is_depot": false,
      "display_x": null,
      "display_y": null
    },
    {
      "node_id": 401,
      "x": 7152,
      "y": 2000,
      "z": null,
      "demand": 0,
      "is_depot": false,
      "display_x": null,
      "display_y": null
    },
    {
      "node_id": 402,
      "x": 7822,
      "y": 1992,
      "z": null,
      "demand": 0,
      "is_depot": false,
      "display_x": null,
      "display_y": null
    },
    {
      "node_id": 403,
      "x": 7416,
      "y": 1953,
      "z": null,
      "demand": 0,
      "is_depot": false,
      "display_x": null,
      "display_y": null
    },
    {
      "node_id": 404,
      "x": 7352,
      "y": 1952,
      "z": null,
      "demand": 0,
      "is_depot": false,
      "display_x": null,
      "display_y": null
    },
    {
      "node_id": 405,
      "x": 354,
      "y": 1950,
      "z": null,
      "demand": 0,
      "is_depot": false,
      "display_x": null,
      "display_y": null
    },
    {
      "node_id": 406,
      "x": 6493,
      "y": 1931,
      "z": null,
      "demand": 0,
      "is_depot": false,
      "display_x": null,
      "display_y": null
    },
    {
      "node_id": 407,
      "x": 7905,
      "y": 1921,
      "z": null,
      "demand": 0,
      "is_depot": false,
      "display_x": null,
      "display_y": null
    },
    {
      "node_id": 408,
      "x": 8229,
      "y": 1905,
      "z": null,
      "demand": 0,
      "is_depot": false,
      "display_x": null,
      "display_y": null
    },
    {
      "node_id": 409,
      "x": 6803,
      "y": 1886,
      "z": null,
      "demand": 0,
      "is_depot": false,
      "display_x": null,
      "display_y": null
    },
    {
      "node_id": 410,
      "x": 4012,
      "y": 1886,
      "z": null,
      "demand": 0,
      "is_depot": false,
      "display_x": null,
      "display_y": null
    },
    {
      "node_id": 411,
      "x": 4759,
      "y": 1883,
      "z": null,
      "demand": 0,
      "is_depot": false,
      "display_x": null,
      "display_y": null
    },
    {
      "node_id": 412,
      "x": 8101,
      "y": 1876,
      "z": null,
      "demand": 0,
      "is_depot": false,
      "display_x": null,
      "display_y": null
    },
    {
      "node_id": 413,
      "x": 7989,
      "y": 1876,
      "z": null,
      "demand": 0,
      "is_depot": false,
      "display_x": null,
      "display_y": null
    },
    {
      "node_id": 414,
      "x": 8063,
      "y": 1860,
      "z": null,
      "demand": 0,
      "is_depot": false,
      "display_x": null,
      "display_y": null
    },
    {
      "node_id": 415,
      "x": 8080,
      "y": 1835,
      "z": null,
      "demand": 0,
      "is_depot": false,
      "display_x": null,
      "display_y": null
    },
    {
      "node_id": 416,
      "x": 7004,
      "y": 1805,
      "z": null,
      "demand": 0,
      "is_depot": false,
      "display_x": null,
      "display_y": null
    },
    {
      "node_id": 417,
      "x": 6252,
      "y": 1795,
      "z": null,
      "demand": 0,
      "is_depot": false,
      "display_x": null,
      "display_y": null
    },
    {
      "node_id": 418,
      "x": 6826,
      "y": 1774,
      "z": null,
      "demand": 0,
      "is_depot": false,
      "display_x": null,
      "display_y": null
    },
    {
      "node_id": 419,
      "x": 7218,
      "y": 1773,
      "z": null,
      "demand": 0,
      "is_depot": false,
      "display_x": null,
      "display_y": null
    },
    {
      "node_id": 420,
      "x": 464,
      "y": 1773,
      "z": null,
      "demand": 0,
      "is_depot": false,
      "display_x": null,
      "display_y": null
    },
    {
      "node_id": 421,
      "x": 809,
      "y": 1766,
      "z": null,
      "demand": 0,
      "is_depot": false,
      "display_x": null,
      "display_y": null
    },
    {
      "node_id": 422,
      "x": 7240,
      "y": 1762,
      "z": null,
      "demand": 0,
      "is_depot": false,
      "display_x": null,
      "display_y": null
    },
    {
      "node_id": 423,
      "x": 7046,
      "y": 1757,
      "z": null,
      "demand": 0,
      "is_depot": false,
      "display_x": null,
      "display_y": null
    },
    {
      "node_id": 424,
      "x": 8098,
      "y": 1746,
      "z": null,
      "demand": 0,
      "is_depot": false,
      "display_x": null,
      "display_y": null
    },
    {
      "node_id": 425,
      "x": 7314,
      "y": 1739,
      "z": null,
      "demand": 0,
      "is_depot": false,
      "display_x": null,
      "display_y": null
    },
    {
      "node_id": 426,
      "x": 7035,
      "y": 1733,
      "z": null,
      "demand": 0,
      "is_depot": false,
      "display_x": null,
      "display_y": null
    },
    {
      "node_id": 427,
      "x": 5506,
      "y": 1719,
      "z": null,
      "demand": 0,
      "is_depot": false,
      "display_x": null,
      "display_y": null
    },
    {
      "node_id": 428,
      "x": 8184,
      "y": 1685,
      "z": null,
      "demand": 0,
      "is_depot": false,
      "display_x": null,
      "display_y": null
    },
    {
      "node_id": 429,
      "x": 6932,
      "y": 1683,
      "z": null,
      "demand": 0,
      "is_depot": false,
      "display_x": null,
      "display_y": null
    },
    {
      "node_id": 430,
      "x": 5914,
      "y": 1682,
      "z": null,
      "demand": 0,
      "is_depot": false,
      "display_x": null,
      "display_y": null
    },
    {
      "node_id": 431,
      "x": 2908,
      "y": 1681,
      "z": null,
      "demand": 0,
      "is_depot": false,
      "display_x": null,
      "display_y": null
    },
    {
      "node_id": 432,
      "x": 6496,
      "y": 1678,
      "z": null,
      "demand": 0,
      "is_depot": false,
      "display_x": null,
      "display_y": null
    },
    {
      "node_id": 433,
      "x": 8525,
      "y": 1664,
      "z": null,
      "demand": 0,
      "is_depot": false,
      "display_x": null,
      "display_y": null
    },
    {
      "node_id": 434,
      "x": 6765,
      "y": 1663,
      "z": null,
      "demand": 0,
      "is_depot": false,
      "display_x": null,
      "display_y": null
    },
    {
      "node_id": 435,
      "x": 7985,
      "y": 1657,
      "z": null,
      "demand": 0,
      "is_depot": false,
      "display_x": null,
      "display_y": null
    },
    {
      "node_id": 436,
      "x": 6854,
      "y": 1640,
      "z": null,
      "demand": 0,
      "is_depot": false,
      "display_x": null,
      "display_y": null
    },
    {
      "node_id": 437,
      "x": 7926,
      "y": 1627,
      "z": null,
      "demand": 0,
      "is_depot": false,
      "display_x": null,
      "display_y": null
    },
    {
      "node_id": 438,
      "x": 7973,
      "y": 1606,
      "z": null,
      "demand": 0,
      "is_depot": false,
      "display_x": null,
      "display_y": null
    },
    {
      "node_id": 439,
      "x": 5060,
      "y": 1577,
      "z": null,
      "demand": 0,
      "is_depot": false,
      "display_x": null,
      "display_y": null
    },
    {
      "node_id": 440,
      "x": 4056,
      "y": 1564,
      "z": null,
      "demand": 0,
      "is_depot": false,
      "display_x": null,
      "display_y": null
    },
    {
      "node_id": 441,
      "x": 5637,
      "y": 1558,
      "z": null,
      "demand": 0,
      "is_depot": false,
      "display_x": null,
      "display_y": null
    },
    {
      "node_id": 442,
      "x": 2011,
      "y": 1558,
      "z": null,
      "demand": 0,
      "is_depot": false,
      "display_x": null,
      "display_y": null
    },
    {
      "node_id": 443,
      "x": 8038,
      "y": 1535,
      "z": null,
      "demand": 0,
      "is_depot": false,
      "display_x": null,
      "display_y": null
    },
    {
      "node_id": 444,
      "x": 6651,
      "y": 1534,
      "z": null,
      "demand": 0,
      "is_depot": false,
      "display_x": null,
      "display_y": null
    },
    {
      "node_id": 445,
      "x": 552,
      "y": 1526,
      "z": null,
      "demand": 0,
      "is_depot": false,
      "display_x": null,
      "display_y": null
    },
    {
      "node_id": 446,
      "x": 6621,
      "y": 1513,
      "z": null,
      "demand": 0,
      "is_depot": false,
      "display_x": null,
      "display_y": null
    },
    {
      "node_id": 447,
      "x": 8594,
      "y": 1510,
      "z": null,
      "demand": 0,
      "is_depot": false,
      "display_x": null,
      "display_y": null
    },
    {
      "node_id": 448,
      "x": 4719,
      "y": 1504,
      "z": null,
      "demand": 0,
      "is_depot": false,
      "display_x": null,
      "display_y": null
    },
    {
      "node_id": 449,
      "x": 5472,
      "y": 1482,
      "z": null,
      "demand": 0,
      "is_depot": false,
      "display_x": null,
      "display_y": null
    },
    {
      "node_id": 450,
      "x": 8605,
      "y": 1479,
      "z": null,
      "demand": 0,
      "is_depot": false,
      "display_x": null,
      "display_y": null
    },
    {
      "node_id": 451,
      "x": 345,
      "y": 1476,
      "z": null,
      "demand": 0,
      "is_depot": false,
      "display_x": null,
      "display_y": null
    },
    {
      "node_id": 452,
      "x": 8228,
      "y": 1471,
      "z": null,
      "demand": 0,
      "is_depot": false,
      "display_x": null,
      "display_y": null
    },
    {
      "node_id": 453,
      "x": 5005,
      "y": 1458,
      "z": null,
      "demand": 0,
      "is_depot": false,
      "display_x": null,
      "display_y": null
    },
    {
      "node_id": 454,
      "x": 5114,
      "y": 1430,
      "z": null,
      "demand": 0,
      "is_depot": false,
      "display_x": null,
      "display_y": null
    },
    {
      "node_id": 455,
      "x": 5964,
      "y": 1421,
      "z": null,
      "demand": 0,
      "is_depot": false,
      "display_x": null,
      "display_y": null
    },
    {
      "node_id": 456,
      "x": 602,
      "y": 1395,
      "z": null,
      "demand": 0,
      "is_depot": false,
      "display_x": null,
      "display_y": null
    },
    {
      "node_id": 457,
      "x": 5098,
      "y": 1394,
      "z": null,
      "demand": 0,
      "is_depot": false,
      "display_x": null,
      "display_y": null
    },
    {
      "node_id": 458,
      "x": 5068,
      "y": 1390,
      "z": null,
      "demand": 0,
      "is_depot": false,
      "display_x": null,
      "display_y": null
    },
    {
      "node_id": 459,
      "x": 8292,
      "y": 1383,
      "z": null,
      "demand": 0,
      "is_depot": false,
      "display_x": null,
      "display_y": null
    },
    {
      "node_id": 460,
      "x": 6258,
      "y": 1354,
      "z": null,
      "demand": 0,
      "is_depot": false,
      "display_x": null,
      "display_y": null
    },
    {
      "node_id": 461,
      "x": 5010,
      "y": 1351,
      "z": null,
      "demand": 0,
      "is_depot": false,
      "display_x": null,
      "display_y": null
    },
    {
      "node_id": 462,
      "x": 6494,
      "y": 1347,
      "z": null,
      "demand": 0,
      "is_depot": false,
      "display_x": null,
      "display_y": null
    },
    {
      "node_id": 463,
      "x": 437,
      "y": 1344,
      "z": null,
      "demand": 0,
      "is_depot": false,
      "display_x": null,
      "display_y": null
    },
    {
      "node_id": 464,
      "x": 413,
      "y": 1338,
      "z": null,
      "demand": 0,
      "is_depot": false,
      "display_x": null,
      "display_y": null
    },
    {
      "node_id": 465,
      "x": 659,
      "y": 1331,
      "z": null,
      "demand": 0,
      "is_depot": false,
      "display_x": null,
      "display_y": null
    },
    {
      "node_id": 466,
      "x": 5840,
      "y": 1325,
      "z": null,
      "demand": 0,
      "is_depot": false,
      "display_x": null,
      "display_y": null
    },
    {
      "node_id": 467,
      "x": 6378,
      "y": 1314,
      "z": null,
      "demand": 0,
      "is_depot": false,
      "display_x": null,
      "display_y": null
    },
    {
      "node_id": 468,
      "x": 6379,
      "y": 1302,
      "z": null,
      "demand": 0,
      "is_depot": false,
      "display_x": null,
      "display_y": null
    },
    {
      "node_id": 469,
      "x": 6359,
      "y": 1298,
      "z": null,
      "demand": 0,
      "is_depot": false,
      "display_x": null,
      "display_y": null
    },
    {
      "node_id": 470,
      "x": 3245,
      "y": 1281,
      "z": null,
      "demand": 0,
      "is_depot": false,
      "display_x": null,
      "display_y": null
    },
    {
      "node_id": 471,
      "x": 450,
      "y": 1274,
      "z": null,
      "demand": 0,
      "is_depot": false,
      "display_x": null,
      "display_y": null
    },
    {
      "node_id": 472,
      "x": 478,
      "y": 1256,
      "z": null,
      "demand": 0,
      "is_depot": false,
      "display_x": null,
      "display_y": null
    },
    {
      "node_id": 473,
      "x": 5571,
      "y": 1255,
      "z": null,
      "demand": 0,
      "is_depot": false,
      "display_x": null,
      "display_y": null
    },
    {
      "node_id": 474,
      "x": 489,
      "y": 1254,
      "z": null,
      "demand": 0,
      "is_depot": false,
      "display_x": null,
      "display_y": null
    },
    {
      "node_id": 475,
      "x": 513,
      "y": 1247,
      "z": null,
      "demand": 0,
      "is_depot": false,
      "display_x": null,
      "display_y": null
    },
    {
      "node_id": 476,
      "x": 6136,
      "y": 1243,
      "z": null,
      "demand": 0,
      "is_depot": false,
      "display_x": null,
      "display_y": null
    },
    {
      "node_id": 477,
      "x": 4170,
      "y": 1232,
      "z": null,
      "demand": 0,
      "is_depot": false,
      "display_x": null,
      "display_y": null
    },
    {
      "node_id": 478,
      "x": 1721,
      "y": 1165,
      "z": null,
      "demand": 0,
      "is_depot": false,
      "display_x": null,
      "display_y": null
    },
    {
      "node_id": 479,
      "x": 893,
      "y": 1161,
      "z": null,
      "demand": 0,
      "is_depot": false,
      "display_x": null,
      "display_y": null
    },
    {
      "node_id": 480,
      "x": 5930,
      "y": 1151,
      "z": null,
      "demand": 0,
      "is_depot": false,
      "display_x": null,
      "display_y": null
    },
    {
      "node_id": 481,
      "x": 4619,
      "y": 1132,
      "z": null,
      "demand": 0,
      "is_depot": false,
      "display_x": null,
      "display_y": null
    },
    {
      "node_id": 482,
      "x": 4125,
      "y": 1125,
      "z": null,
      "demand": 0,
      "is_depot": false,
      "display_x": null,
      "display_y": null
    },
    {
      "node_id": 483,
      "x": 5139,
      "y": 1124,
      "z": null,
      "demand": 0,
      "is_depot": false,
      "display_x": null,
      "display_y": null
    },
    {
      "node_id": 484,
      "x": 572,
      "y": 1108,
      "z": null,
      "demand": 0,
      "is_depot": false,
      "display_x": null,
      "display_y": null
    },
    {
      "node_id": 485,
      "x": 4500,
      "y": 1093,
      "z": null,
      "demand": 0,
      "is_depot": false,
      "display_x": null,
      "display_y": null
    },
    {
      "node_id": 486,
      "x": 2372,
      "y": 1084,
      "z": null,
      "demand": 0,
      "is_depot": false,
      "display_x": null,
      "display_y": null
    },
    {
      "node_id": 487,
      "x": 993,
      "y": 1084,
      "z": null,
      "demand": 0,
      "is_depot": false,
      "display_x": null,
      "display_y": null
    },
    {
      "node_id": 488,
      "x": 527,
      "y": 1077,
      "z": null,
      "demand": 0,
      "is_depot": false,
      "display_x": null,
      "display_y": null
    },
    {
      "node_id": 489,
      "x": 5788,
      "y": 1053,
      "z": null,
      "demand": 0,
      "is_depot": false,
      "display_x": null,
      "display_y": null
    },
    {
      "node_id": 490,
      "x": 3719,
      "y": 1043,
      "z": null,
      "demand": 0,
      "is_depot": false,
      "display_x": null,
      "display_y": null
    },
    {
      "node_id": 491,
      "x": 4805,
      "y": 1033,
      "z": null,
      "demand": 0,
      "is_depot": false,
      "display_x": null,
      "display_y": null
    },
    {
      "node_id": 492,
      "x": 5140,
      "y": 1018,
      "z": null,
      "demand": 0,
      "is_depot": false,
      "display_x": null,
      "display_y": null
    },
    {
      "node_id": 493,
      "x": 5344,
      "y": 1003,
      "z": null,
      "demand": 0,
      "is_depot": false,
      "display_x": null,
      "display_y": null
    },
    {
      "node_id": 494,
      "x": 5532,
      "y": 998,
      "z": null,
      "demand": 0,
      "is_depot": false,
      "display_x": null,
      "display_y": null
    },
    {
      "node_id": 495,
      "x": 5069,
      "y": 998,
      "z": null,
      "demand": 0,
      "is_depot": false,
      "display_x": null,
      "display_y": null
    },
    {
      "node_id": 496,
      "x": 1595,
      "y": 942,
      "z": null,
      "demand": 0,
      "is_depot": false,
      "display_x": null,
      "display_y": null
    },
    {
      "node_id": 497,
      "x": 5666,
      "y": 914,
      "z": null,
      "demand": 0,
      "is_depot": false,
      "display_x": null,
      "display_y": null
    },
    {
      "node_id": 498,
      "x": 2260,
      "y": 913,
      "z": null,
      "demand": 0,
      "is_depot": false,
      "display_x": null,
      "display_y": null
    },
    {
      "node_id": 499,
      "x": 4244,
      "y": 896,
      "z": null,
      "demand": 0,
      "is_depot": false,
      "display_x": null,
      "display_y": null
    },
    {
      "node_id": 500,
      "x": 5596,
      "y": 892,
      "z": null,
      "demand": 0,
      "is_depot": false,
      "display_x": null,
      "display_y": null
    },
    {
      "node_id": 501,
      "x": 4569,
      "y": 886,
      "z": null,
      "demand": 0,
      "is_depot": false,
      "display_x": null,
      "display_y": null
    },
    {
      "node_id": 502,
      "x": 1072,
      "y": 883,
      "z": null,
      "demand": 0,
      "is_depot": false,
      "display_x": null,
      "display_y": null
    },
    {
      "node_id": 503,
      "x": 3499,
      "y": 863,
      "z": null,
      "demand": 0,
      "is_depot": false,
      "display_x": null,
      "display_y": null
    },
    {
      "node_id": 504,
      "x": 5136,
      "y": 825,
      "z": null,
      "demand": 0,
      "is_depot": false,
      "display_x": null,
      "display_y": null
    },
    {
      "node_id": 505,
      "x": 783,
      "y": 825,
      "z": null,
      "demand": 0,
      "is_depot": false,
      "display_x": null,
      "display_y": null
    },
    {
      "node_id": 506,
      "x": 834,
      "y": 757,
      "z": null,
      "demand": 0,
      "is_depot": false,
      "display_x": null,
      "display_y": null
    },
    {
      "node_id": 507,
      "x": 1406,
      "y": 750,
      "z": null,
      "demand": 0,
      "is_depot": false,
      "display_x": null,
      "display_y": null
    },
    {
      "node_id": 508,
      "x": 3390,
      "y": 698,
      "z": null,
      "demand": 0,
      "is_depot": false,
      "display_x": null,
      "display_y": null
    },
    {
      "node_id": 509,
      "x": 2384,
      "y": 695,
      "z": null,
      "demand": 0,
      "is_depot": false,
      "display_x": null,
      "display_y": null
    },
    {
      "node_id": 510,
      "x": 982,
      "y": 659,
      "z": null,
      "demand": 0,
      "is_depot": false,
      "display_x": null,
      "display_y": null
    },
    {
      "node_id": 511,
      "x": 1422,
      "y": 658,
      "z": null,
      "demand": 0,
      "is_depot": false,
      "display_x": null,
      "display_y": null
    },
    {
      "node_id": 512,
      "x": 1361,
      "y": 637,
      "z": null,
      "demand": 0,
      "is_depot": false,
      "display_x": null,
      "display_y": null
    },
    {
      "node_id": 513,
      "x": 1926,
      "y": 636,
      "z": null,
      "demand": 0,
      "is_depot": false,
      "display_x": null,
      "display_y": null
    },
    {
      "node_id": 514,
      "x": 1213,
      "y": 633,
      "z": null,
      "demand": 0,
      "is_depot": false,
      "display_x": null,
      "display_y": null
    },
    {
      "node_id": 515,
      "x": 1415,
      "y": 628,
      "z": null,
      "demand": 0,
      "is_depot": false,
      "display_x": null,
      "display_y": null
    },
    {
      "node_id": 516,
      "x": 1082,
      "y": 625,
      "z": null,
      "demand": 0,
      "is_depot": false,
      "display_x": null,
      "display_y": null
    },
    {
      "node_id": 517,
      "x": 1254,
      "y": 617,
      "z": null,
      "demand": 0,
      "is_depot": false,
      "display_x": null,
      "display_y": null
    },
    {
      "node_id": 518,
      "x": 5070,
      "y": 605,
      "z": null,
      "demand": 0,
      "is_depot": false,
      "display_x": null,
      "display_y": null
    },
    {
      "node_id": 519,
      "x": 1212,
      "y": 603,
      "z": null,
      "demand": 0,
      "is_depot": false,
      "display_x": null,
      "display_y": null
    },
    {
      "node_id": 520,
      "x": 1249,
      "y": 600,
      "z": null,
      "demand": 0,
      "is_depot": false,
      "display_x": null,
      "display_y": null
    },
    {
      "node_id": 521,
      "x": 3477,
      "y": 599,
      "z": null,
      "demand": 0,
      "is_depot": false,
      "display_x": null,
      "display_y": null
    },
    {
      "node_id": 522,
      "x": 1322,
      "y": 580,
      "z": null,
      "demand": 0,
      "is_depot": false,
      "display_x": null,
      "display_y": null
    },
    {
      "node_id": 523,
      "x": 1253,
      "y": 580,
      "z": null,
      "demand": 0,
      "is_depot": false,
      "display_x": null,
      "display_y": null
    },
    {
      "node_id": 524,
      "x": 1276,
      "y": 559,
      "z": null,
      "demand": 0,
      "is_depot": false,
      "display_x": null,
      "display_y": null
    },
    {
      "node_id": 525,
      "x": 2647,
      "y": 485,
      "z": null,
      "demand": 0,
      "is_depot": false,
      "display_x": null,
      "display_y": null
    },
    {
      "node_id": 526,
      "x": 1443,
      "y": 459,
      "z": null,
      "demand": 0,
      "is_depot": false,
      "display_x": null,
      "display_y": null
    },
    {
      "node_id": 527,
      "x": 1961,
      "y": 445,
      "z": null,
      "demand": 0,
      "is_depot": false,
      "display_x": null,
      "display_y": null
    },
    {
      "node_id": 528,
      "x": 1790,
      "y": 429,
      "z": null,
      "demand": 0,
      "is_depot": false,
      "display_x": null,
      "display_y": null
    },
    {
      "node_id": 529,
      "x": 1503,
      "y": 362,
      "z": null,
      "demand": 0,
      "is_depot": false,
      "display_x": null,
      "display_y": null
    },
    {
      "node_id": 530,
      "x": 5393,
      "y": 355,
      "z": null,
      "demand": 0,
      "is_depot": false,
      "display_x": null,
      "display_y": null
    },
    {
      "node_id": 531,
      "x": 5469,
      "y": 10,
      "z": null,
      "demand": 0,
      "is_depot": false,
      "display_x": null,
      "display_y": null
    }
  ],
  "tours": [],
  "metadata": {
    "file_path": "datasets_raw/problems/tsp/att532.tsp",
    "file_size": 7391,
    "file_name": "att532.tsp",
    "problem_source": "tsp",
    "has_coordinates": true,
    "has_demands": false,
    "has_depots": false,
    "is_symmetric": true,
    "weight_source": "coordinate_based"
  }
}