{
  "problem": {
    "name": "d198",
    "type": "TSP",
    "comment": "Drilling problem (Reinelt)",
    "dimension": 198,
    "capacity": null,
    "edge_weight_type": "EUC_2D",
    "edge_weight_format": null,
    "node_coord_type": null,
    "display_data_type": null,
    "file_path": "datasets_raw/problems/tsp/d198.tsp",
    "file_size": 5561
  },
  "nodes": [
    {
      "node_id": 0,
      "x": 0.0,
      "y": 0.0,
      "z": null,
      "demand": 0,
      "is_depot": false,
      "display_x": null,
      "display_y": null
    },
    {
      "node_id": 1,
      "x": 551.2,
      "y": 996.4,
      "z": null,
      "demand": 0,
      "is_depot": false,
      "display_x": null,
      "display_y": null
    },
    {
      "node_id": 2,
      "x": 627.4,
      "y": 996.4,
      "z": null,
      "demand": 0,
      "is_depot": false,
      "display_x": null,
      "display_y": null
    },
    {
      "node_id": 3,
      "x": 703.6,
      "y": 996.4,
      "z": null,
      "demand": 0,
      "is_depot": false,
      "display_x": null,
      "display_y": null
    },
    {
      "node_id": 4,
      "x": 703.6,
      "y": 1047.2,
      "z": null,
      "demand": 0,
      "is_depot": false,
      "display_x": null,
      "display_y": null
    },
    {
      "node_id": 5,
      "x": 627.4,
      "y": 1047.2,
      "z": null,
      "demand": 0,
      "is_depot": false,
      "display_x": null,
      "display_y": null
    },
    {
      "node_id": 6,
      "x": 551.2,
      "y": 1047.2,
      "z": null,
      "demand": 0,
      "is_depot": false,
      "display_x": null,
      "display_y": null
    },
    {
      "node_id": 7,
      "x": 881.4,
      "y": 1352.0,
      "z": null,
      "demand": 0,
      "is_depot": false,
      "display_x": null,
      "display_y": null
    },
    {
      "node_id": 8,
      "x": 932.2,
      "y": 1352.0,
      "z": null,
      "demand": 0,
      "is_depot": false,
      "display_x": null,
      "display_y": null
    },
    {
      "node_id": 9,
      "x": 957.6,
      "y": 1352.0,
      "z": null,
      "demand": 0,
      "is_depot": false,
      "display_x": null,
      "display_y": null
    },
    {
      "node_id": 10,
      "x": 983.0,
      "y": 1352.0,
      "z": null,
      "demand": 0,
      "is_depot": false,
      "display_x": null,
      "display_y": null
    },
    {
      "node_id": 11,
      "x": 1008.4,
      "y": 1352.0,
      "z": null,
      "demand": 0,
      "is_depot": false,
      "display_x": null,
      "display_y": null
    },
    {
      "node_id": 12,
      "x": 1033.8,
      "y": 1352.0,
      "z": null,
      "demand": 0,
      "is_depot": false,
      "display_x": null,
      "display_y": null
    },
    {
      "node_id": 13,
      "x": 1313.2,
      "y": 1123.4,
      "z": null,
      "demand": 0,
      "is_depot": false,
      "display_x": null,
      "display_y": null
    },
    {
      "node_id": 14,
      "x": 1287.8,
      "y": 1098.0,
      "z": null,
      "demand": 0,
      "is_depot": false,
      "display_x": null,
      "display_y": null
    },
    {
      "node_id": 15,
      "x": 1287.8,
      "y": 996.4,
      "z": null,
      "demand": 0,
      "is_depot": false,
      "display_x": null,
      "display_y": null
    },
    {
      "node_id": 16,
      "x": 1313.2,
      "y": 996.4,
      "z": null,
      "demand": 0,
      "is_depot": false,
      "display_x": null,
      "display_y": null
    },
    {
      "node_id": 17,
      "x": 1465.6,
      "y": 996.4,
      "z": null,
      "demand": 0,
      "is_depot": false,
      "display_x": null,
      "display_y": null
    },
    {
      "node_id": 18,
      "x": 1516.4,
      "y": 996.4,
      "z": null,
      "demand": 0,
      "is_depot": false,
      "display_x": null,
      "display_y": null
    },
    {
      "node_id": 19,
      "x": 1592.6,
      "y": 996.4,
      "z": null,
      "demand": 0,
      "is_depot": false,
      "display_x": null,
      "display_y": null
    },
    {
      "node_id": 20,
      "x": 1592.6,
      "y": 1098.0,
      "z": null,
      "demand": 0,
      "is_depot": false,
      "display_x": null,
      "display_y": null
    },
    {
      "node_id": 21,
      "x": 1516.4,
      "y": 1098.0,
      "z": null,
      "demand": 0,
      "is_depot": false,
      "display_x": null,
      "display_y": null
    },
    {
      "node_id": 22,
      "x": 1465.6,
      "y": 1098.0,
      "z": null,
      "demand": 0,
      "is_depot": false,
      "display_x": null,
      "display_y": null
    },
    {
      "node_id": 23,
      "x": 1567.2,
      "y": 1123.4,
      "z": null,
      "demand": 0,
      "is_depot": false,
      "display_x": null,
      "display_y": null
    },
    {
      "node_id": 24,
      "x": 1592.6,
      "y": 1148.8,
      "z": null,
      "demand": 0,
      "is_depot": false,
      "display_x": null,
      "display_y": null
    },
    {
      "node_id": 25,
      "x": 1567.2,
      "y": 1174.2,
      "z": null,
      "demand": 0,
      "is_depot": false,
      "display_x": null,
      "display_y": null
    },
    {
      "node_id": 26,
      "x": 1541.8,
      "y": 1174.2,
      "z": null,
      "demand": 0,
      "is_depot": false,
      "display_x": null,
      "display_y": null
    },
    {
      "node_id": 27,
      "x": 1491.0,
      "y": 1174.2,
      "z": null,
      "demand": 0,
      "is_depot": false,
      "display_x": null,
      "display_y": null
    },
    {
      "node_id": 28,
      "x": 1440.2,
      "y": 1174.2,
      "z": null,
      "demand": 0,
      "is_depot": false,
      "display_x": null,
      "display_y": null
    },
    {
      "node_id": 29,
      "x": 1465.6,
      "y": 1199.6,
      "z": null,
      "demand": 0,
      "is_depot": false,
      "display_x": null,
      "display_y": null
    },
    {
      "node_id": 30,
      "x": 1414.8,
      "y": 1225.0,
      "z": null,
      "demand": 0,
      "is_depot": false,
      "display_x": null,
      "display_y": null
    },
    {
      "node_id": 31,
      "x": 1440.2,
      "y": 1225.0,
      "z": null,
      "demand": 0,
      "is_depot": false,
      "display_x": null,
      "display_y": null
    },
    {
      "node_id": 32,
      "x": 1491.0,
      "y": 1225.0,
      "z": null,
      "demand": 0,
      "is_depot": false,
      "display_x": null,
      "display_y": null
    },
    {
      "node_id": 33,
      "x": 1516.4,
      "y": 1225.0,
      "z": null,
      "demand": 0,
      "is_depot": false,
      "display_x": null,
      "display_y": null
    },
    {
      "node_id": 34,
      "x": 1592.6,
      "y": 1250.4,
      "z": null,
      "demand": 0,
      "is_depot": false,
      "display_x": null,
      "display_y": null
    },
    {
      "node_id": 35,
      "x": 1465.6,
      "y": 1250.4,
      "z": null,
      "demand": 0,
      "is_depot": false,
      "display_x": null,
      "display_y": null
    },
    {
      "node_id": 36,
      "x": 1440.2,
      "y": 1250.4,
      "z": null,
      "demand": 0,
      "is_depot": false,
      "display_x": null,
      "display_y": null
    },
    {
      "node_id": 37,
      "x": 1389.4,
      "y": 1250.4,
      "z": null,
      "demand": 0,
      "is_depot": false,
      "display_x": null,
      "display_y": null
    },
    {
      "node_id": 38,
      "x": 1541.8,
      "y": 1275.8,
      "z": null,
      "demand": 0,
      "is_depot": false,
      "display_x": null,
      "display_y": null
    },
    {
      "node_id": 39,
      "x": 1160.8,
      "y": 1123.4,
      "z": null,
      "demand": 0,
      "is_depot": false,
      "display_x": null,
      "display_y": null
    },
    {
      "node_id": 40,
      "x": 1160.8,
      "y": 1225.0,
      "z": null,
      "demand": 0,
      "is_depot": false,
      "display_x": null,
      "display_y": null
    },
    {
      "node_id": 41,
      "x": 1262.4,
      "y": 1301.2,
      "z": null,
      "demand": 0,
      "is_depot": false,
      "display_x": null,
      "display_y": null
    },
    {
      "node_id": 42,
      "x": 1287.8,
      "y": 1301.2,
      "z": null,
      "demand": 0,
      "is_depot": false,
      "display_x": null,
      "display_y": null
    },
    {
      "node_id": 43,
      "x": 1338.6,
      "y": 1301.2,
      "z": null,
      "demand": 0,
      "is_depot": false,
      "display_x": null,
      "display_y": null
    },
    {
      "node_id": 44,
      "x": 1414.8,
      "y": 1301.2,
      "z": null,
      "demand": 0,
      "is_depot": false,
      "display_x": null,
      "display_y": null
    },
    {
      "node_id": 45,
      "x": 1491.0,
      "y": 1301.2,
      "z": null,
      "demand": 0,
      "is_depot": false,
      "display_x": null,
      "display_y": null
    },
    {
      "node_id": 46,
      "x": 1541.8,
      "y": 1301.2,
      "z": null,
      "demand": 0,
      "is_depot": false,
      "display_x": null,
      "display_y": null
    },
    {
      "node_id": 47,
      "x": 1643.4,
      "y": 1301.2,
      "z": null,
      "demand": 0,
      "is_depot": false,
      "display_x": null,
      "display_y": null
    },
    {
      "node_id": 48,
      "x": 1668.8,
      "y": 1326.6,
      "z": null,
      "demand": 0,
      "is_depot": false,
      "display_x": null,
      "display_y": null
    },
    {
      "node_id": 49,
      "x": 1618.0,
      "y": 1326.6,
      "z": null,
      "demand": 0,
      "is_depot": false,
      "display_x": null,
      "display_y": null
    },
    {
      "node_id": 50,
      "x": 1567.2,
      "y": 1326.6,
      "z": null,
      "demand": 0,
      "is_depot": false,
      "display_x": null,
      "display_y": null
    },
    {
      "node_id": 51,
      "x": 1516.4,
      "y": 1326.6,
      "z": null,
      "demand": 0,
      "is_depot": false,
      "display_x": null,
      "display_y": null
    },
    {
      "node_id": 52,
      "x": 1465.6,
      "y": 1326.6,
      "z": null,
      "demand": 0,
      "is_depot": false,
      "display_x": null,
      "display_y": null
    },
    {
      "node_id": 53,
      "x": 1414.8,
      "y": 1326.6,
      "z": null,
      "demand": 0,
      "is_depot": false,
      "display_x": null,
      "display_y": null
    },
    {
      "node_id": 54,
      "x": 1338.6,
      "y": 1326.6,
      "z": null,
      "demand": 0,
      "is_depot": false,
      "display_x": null,
      "display_y": null
    },
    {
      "node_id": 55,
      "x": 1313.2,
      "y": 1326.6,
      "z": null,
      "demand": 0,
      "is_depot": false,
      "display_x": null,
      "display_y": null
    },
    {
      "node_id": 56,
      "x": 1237.0,
      "y": 1326.6,
      "z": null,
      "demand": 0,
      "is_depot": false,
      "display_x": null,
      "display_y": null
    },
    {
      "node_id": 57,
      "x": 1237.0,
      "y": 1352.0,
      "z": null,
      "demand": 0,
      "is_depot": false,
      "display_x": null,
      "display_y": null
    },
    {
      "node_id": 58,
      "x": 1313.2,
      "y": 1352.0,
      "z": null,
      "demand": 0,
      "is_depot": false,
      "display_x": null,
      "display_y": null
    },
    {
      "node_id": 59,
      "x": 1338.6,
      "y": 1352.0,
      "z": null,
      "demand": 0,
      "is_depot": false,
      "display_x": null,
      "display_y": null
    },
    {
      "node_id": 60,
      "x": 1414.8,
      "y": 1352.0,
      "z": null,
      "demand": 0,
      "is_depot": false,
      "display_x": null,
      "display_y": null
    },
    {
      "node_id": 61,
      "x": 1465.6,
      "y": 1352.0,
      "z": null,
      "demand": 0,
      "is_depot": false,
      "display_x": null,
      "display_y": null
    },
    {
      "node_id": 62,
      "x": 1694.2,
      "y": 1352.0,
      "z": null,
      "demand": 0,
      "is_depot": false,
      "display_x": null,
      "display_y": null
    },
    {
      "node_id": 63,
      "x": 1618.0,
      "y": 1377.4,
      "z": null,
      "demand": 0,
      "is_depot": false,
      "display_x": null,
      "display_y": null
    },
    {
      "node_id": 64,
      "x": 1516.4,
      "y": 1377.4,
      "z": null,
      "demand": 0,
      "is_depot": false,
      "display_x": null,
      "display_y": null
    },
    {
      "node_id": 65,
      "x": 1414.8,
      "y": 1377.4,
      "z": null,
      "demand": 0,
      "is_depot": false,
      "display_x": null,
      "display_y": null
    },
    {
      "node_id": 66,
      "x": 1338.6,
      "y": 1377.4,
      "z": null,
      "demand": 0,
      "is_depot": false,
      "display_x": null,
      "display_y": null
    },
    {
      "node_id": 67,
      "x": 1313.2,
      "y": 1377.4,
      "z": null,
      "demand": 0,
      "is_depot": false,
      "display_x": null,
      "display_y": null
    },
    {
      "node_id": 68,
      "x": 1237.0,
      "y": 1377.4,
      "z": null,
      "demand": 0,
      "is_depot": false,
      "display_x": null,
      "display_y": null
    },
    {
      "node_id": 69,
      "x": 1357.7,
      "y": 1390.1,
      "z": null,
      "demand": 0,
      "is_depot": false,
      "display_x": null,
      "display_y": null
    },
    {
      "node_id": 70,
      "x": 1237.0,
      "y": 1402.8,
      "z": null,
      "demand": 0,
      "is_depot": false,
      "display_x": null,
      "display_y": null
    },
    {
      "node_id": 71,
      "x": 1313.2,
      "y": 1402.8,
      "z": null,
      "demand": 0,
      "is_depot": false,
      "display_x": null,
      "display_y": null
    },
    {
      "node_id": 72,
      "x": 1338.6,
      "y": 1402.8,
      "z": null,
      "demand": 0,
      "is_depot": false,
      "display_x": null,
      "display_y": null
    },
    {
      "node_id": 73,
      "x": 1414.8,
      "y": 1402.8,
      "z": null,
      "demand": 0,
      "is_depot": false,
      "display_x": null,
      "display_y": null
    },
    {
      "node_id": 74,
      "x": 1465.6,
      "y": 1402.8,
      "z": null,
      "demand": 0,
      "is_depot": false,
      "display_x": null,
      "display_y": null
    },
    {
      "node_id": 75,
      "x": 1567.2,
      "y": 1402.8,
      "z": null,
      "demand": 0,
      "is_depot": false,
      "display_x": null,
      "display_y": null
    },
    {
      "node_id": 76,
      "x": 1592.6,
      "y": 1402.8,
      "z": null,
      "demand": 0,
      "is_depot": false,
      "display_x": null,
      "display_y": null
    },
    {
      "node_id": 77,
      "x": 1618.0,
      "y": 1402.8,
      "z": null,
      "demand": 0,
      "is_depot": false,
      "display_x": null,
      "display_y": null
    },
    {
      "node_id": 78,
      "x": 1694.2,
      "y": 1428.2,
      "z": null,
      "demand": 0,
      "is_depot": false,
      "display_x": null,
      "display_y": null
    },
    {
      "node_id": 79,
      "x": 1668.8,
      "y": 1428.2,
      "z": null,
      "demand": 0,
      "is_depot": false,
      "display_x": null,
      "display_y": null
    },
    {
      "node_id": 80,
      "x": 1541.8,
      "y": 1428.2,
      "z": null,
      "demand": 0,
      "is_depot": false,
      "display_x": null,
      "display_y": null
    },
    {
      "node_id": 81,
      "x": 1440.2,
      "y": 1428.2,
      "z": null,
      "demand": 0,
      "is_depot": false,
      "display_x": null,
      "display_y": null
    },
    {
      "node_id": 82,
      "x": 1414.8,
      "y": 1428.2,
      "z": null,
      "demand": 0,
      "is_depot": false,
      "display_x": null,
      "display_y": null
    },
    {
      "node_id": 83,
      "x": 1338.6,
      "y": 1428.2,
      "z": null,
      "demand": 0,
      "is_depot": false,
      "display_x": null,
      "display_y": null
    },
    {
      "node_id": 84,
      "x": 1262.4,
      "y": 1428.2,
      "z": null,
      "demand": 0,
      "is_depot": false,
      "display_x": null,
      "display_y": null
    },
    {
      "node_id": 85,
      "x": 1237.0,
      "y": 1453.6,
      "z": null,
      "demand": 0,
      "is_depot": false,
      "display_x": null,
      "display_y": null
    },
    {
      "node_id": 86,
      "x": 1338.6,
      "y": 1453.6,
      "z": null,
      "demand": 0,
      "is_depot": false,
      "display_x": null,
      "display_y": null
    },
    {
      "node_id": 87,
      "x": 1414.8,
      "y": 1453.6,
      "z": null,
      "demand": 0,
      "is_depot": false,
      "display_x": null,
      "display_y": null
    },
    {
      "node_id": 88,
      "x": 1465.6,
      "y": 1453.6,
      "z": null,
      "demand": 0,
      "is_depot": false,
      "display_x": null,
      "display_y": null
    },
    {
      "node_id": 89,
      "x": 1491.0,
      "y": 1453.6,
      "z": null,
      "demand": 0,
      "is_depot": false,
      "display_x": null,
      "display_y": null
    },
    {
      "node_id": 90,
      "x": 1668.8,
      "y": 1453.6,
      "z": null,
      "demand": 0,
      "is_depot": false,
      "display_x": null,
      "display_y": null
    },
    {
      "node_id": 91,
      "x": 1694.2,
      "y": 1453.6,
      "z": null,
      "demand": 0,
      "is_depot": false,
      "display_x": null,
      "display_y": null
    },
    {
      "node_id": 92,
      "x": 1618.0,
      "y": 1479.0,
      "z": null,
      "demand": 0,
      "is_depot": false,
      "display_x": null,
      "display_y": null
    },
    {
      "node_id": 93,
      "x": 1592.6,
      "y": 1479.0,
      "z": null,
      "demand": 0,
      "is_depot": false,
      "display_x": null,
      "display_y": null
    },
    {
      "node_id": 94,
      "x": 1567.2,
      "y": 1479.0,
      "z": null,
      "demand": 0,
      "is_depot": false,
      "display_x": null,
      "display_y": null
    },
    {
      "node_id": 95,
      "x": 1516.4,
      "y": 1479.0,
      "z": null,
      "demand": 0,
      "is_depot": false,
      "display_x": null,
      "display_y": null
    },
    {
      "node_id": 96,
      "x": 1440.2,
      "y": 1479.0,
      "z": null,
      "demand": 0,
      "is_depot": false,
      "display_x": null,
      "display_y": null
    },
    {
      "node_id": 97,
      "x": 1414.8,
      "y": 1479.0,
      "z": null,
      "demand": 0,
      "is_depot": false,
      "display_x": null,
      "display_y": null
    },
    {
      "node_id": 98,
      "x": 1338.6,
      "y": 1479.0,
      "z": null,
      "demand": 0,
      "is_depot": false,
      "display_x": null,
      "display_y": null
    },
    {
      "node_id": 99,
      "x": 1262.4,
      "y": 1479.0,
      "z": null,
      "demand": 0,
      "is_depot": false,
      "display_x": null,
      "display_y": null
    },
    {
      "node_id": 100,
      "x": 1592.6,
      "y": 1504.4,
      "z": null,
      "demand": 0,
      "is_depot": false,
      "display_x": null,
      "display_y": null
    },
    {
      "node_id": 101,
      "x": 1618.0,
      "y": 1504.4,
      "z": null,
      "demand": 0,
      "is_depot": false,
      "display_x": null,
      "display_y": null
    },
    {
      "node_id": 102,
      "x": 1668.8,
      "y": 1529.8,
      "z": null,
      "demand": 0,
      "is_depot": false,
      "display_x": null,
      "display_y": null
    },
    {
      "node_id": 103,
      "x": 1694.2,
      "y": 1529.8,
      "z": null,
      "demand": 0,
      "is_depot": false,
      "display_x": null,
      "display_y": null
    },
    {
      "node_id": 104,
      "x": 1745.0,
      "y": 1529.8,
      "z": null,
      "demand": 0,
      "is_depot": false,
      "display_x": null,
      "display_y": null
    },
    {
      "node_id": 105,
      "x": 1821.2,
      "y": 1529.8,
      "z": null,
      "demand": 0,
      "is_depot": false,
      "display_x": null,
      "display_y": null
    },
    {
      "node_id": 106,
      "x": 1846.6,
      "y": 1529.8,
      "z": null,
      "demand": 0,
      "is_depot": false,
      "display_x": null,
      "display_y": null
    },
    {
      "node_id": 107,
      "x": 1948.2,
      "y": 1529.8,
      "z": null,
      "demand": 0,
      "is_depot": false,
      "display_x": null,
      "display_y": null
    },
    {
      "node_id": 108,
      "x": 1922.8,
      "y": 1555.2,
      "z": null,
      "demand": 0,
      "is_depot": false,
      "display_x": null,
      "display_y": null
    },
    {
      "node_id": 109,
      "x": 1897.4,
      "y": 1555.2,
      "z": null,
      "demand": 0,
      "is_depot": false,
      "display_x": null,
      "display_y": null
    },
    {
      "node_id": 110,
      "x": 1872.0,
      "y": 1555.2,
      "z": null,
      "demand": 0,
      "is_depot": false,
      "display_x": null,
      "display_y": null
    },
    {
      "node_id": 111,
      "x": 1821.2,
      "y": 1555.2,
      "z": null,
      "demand": 0,
      "is_depot": false,
      "display_x": null,
      "display_y": null
    },
    {
      "node_id": 112,
      "x": 1795.8,
      "y": 1555.2,
      "z": null,
      "demand": 0,
      "is_depot": false,
      "display_x": null,
      "display_y": null
    },
    {
      "node_id": 113,
      "x": 1770.4,
      "y": 1555.2,
      "z": null,
      "demand": 0,
      "is_depot": false,
      "display_x": null,
      "display_y": null
    },
    {
      "node_id": 114,
      "x": 1770.4,
      "y": 1656.8,
      "z": null,
      "demand": 0,
      "is_depot": false,
      "display_x": null,
      "display_y": null
    },
    {
      "node_id": 115,
      "x": 1795.8,
      "y": 1656.8,
      "z": null,
      "demand": 0,
      "is_depot": false,
      "display_x": null,
      "display_y": null
    },
    {
      "node_id": 116,
      "x": 1821.2,
      "y": 1656.8,
      "z": null,
      "demand": 0,
      "is_depot": false,
      "display_x": null,
      "display_y": null
    },
    {
      "node_id": 117,
      "x": 1872.0,
      "y": 1656.8,
      "z": null,
      "demand": 0,
      "is_depot": false,
      "display_x": null,
      "display_y": null
    },
    {
      "node_id": 118,
      "x": 1897.4,
      "y": 1656.8,
      "z": null,
      "demand": 0,
      "is_depot": false,
      "display_x": null,
      "display_y": null
    },
    {
      "node_id": 119,
      "x": 1922.8,
      "y": 1656.8,
      "z": null,
      "demand": 0,
      "is_depot": false,
      "display_x": null,
      "display_y": null
    },
    {
      "node_id": 120,
      "x": 1808.5,
      "y": 1694.9,
      "z": null,
      "demand": 0,
      "is_depot": false,
      "display_x": null,
      "display_y": null
    },
    {
      "node_id": 121,
      "x": 1757.7,
      "y": 1694.9,
      "z": null,
      "demand": 0,
      "is_depot": false,
      "display_x": null,
      "display_y": null
    },
    {
      "node_id": 122,
      "x": 1884.7,
      "y": 1733.0,
      "z": null,
      "demand": 0,
      "is_depot": false,
      "display_x": null,
      "display_y": null
    },
    {
      "node_id": 123,
      "x": 1999.0,
      "y": 1733.0,
      "z": null,
      "demand": 0,
      "is_depot": false,
      "display_x": null,
      "display_y": null
    },
    {
      "node_id": 124,
      "x": 2075.2,
      "y": 1733.0,
      "z": null,
      "demand": 0,
      "is_depot": false,
      "display_x": null,
      "display_y": null
    },
    {
      "node_id": 125,
      "x": 2113.3,
      "y": 1733.0,
      "z": null,
      "demand": 0,
      "is_depot": false,
      "display_x": null,
      "display_y": null
    },
    {
      "node_id": 126,
      "x": 2176.8,
      "y": 1733.0,
      "z": null,
      "demand": 0,
      "is_depot": false,
      "display_x": null,
      "display_y": null
    },
    {
      "node_id": 127,
      "x": 2236.5,
      "y": 1733.0,
      "z": null,
      "demand": 0,
      "is_depot": false,
      "display_x": null,
      "display_y": null
    },
    {
      "node_id": 128,
      "x": 2176.8,
      "y": 1783.8,
      "z": null,
      "demand": 0,
      "is_depot": false,
      "display_x": null,
      "display_y": null
    },
    {
      "node_id": 129,
      "x": 2126.0,
      "y": 1783.8,
      "z": null,
      "demand": 0,
      "is_depot": false,
      "display_x": null,
      "display_y": null
    },
    {
      "node_id": 130,
      "x": 2100.6,
      "y": 1783.8,
      "z": null,
      "demand": 0,
      "is_depot": false,
      "display_x": null,
      "display_y": null
    },
    {
      "node_id": 131,
      "x": 2100.6,
      "y": 1809.2,
      "z": null,
      "demand": 0,
      "is_depot": false,
      "display_x": null,
      "display_y": null
    },
    {
      "node_id": 132,
      "x": 2126.0,
      "y": 1809.2,
      "z": null,
      "demand": 0,
      "is_depot": false,
      "display_x": null,
      "display_y": null
    },
    {
      "node_id": 133,
      "x": 2100.6,
      "y": 1834.6,
      "z": null,
      "demand": 0,
      "is_depot": false,
      "display_x": null,
      "display_y": null
    },
    {
      "node_id": 134,
      "x": 2126.0,
      "y": 1834.6,
      "z": null,
      "demand": 0,
      "is_depot": false,
      "display_x": null,
      "display_y": null
    },
    {
      "node_id": 135,
      "x": 2151.4,
      "y": 1834.6,
      "z": null,
      "demand": 0,
      "is_depot": false,
      "display_x": null,
      "display_y": null
    },
    {
      "node_id": 136,
      "x": 2236.5,
      "y": 1847.3,
      "z": null,
      "demand": 0,
      "is_depot": false,
      "display_x": null,
      "display_y": null
    },
    {
      "node_id": 137,
      "x": 1999.0,
      "y": 1847.3,
      "z": null,
      "demand": 0,
      "is_depot": false,
      "display_x": null,
      "display_y": null
    },
    {
      "node_id": 138,
      "x": 1884.7,
      "y": 1847.3,
      "z": null,
      "demand": 0,
      "is_depot": false,
      "display_x": null,
      "display_y": null
    },
    {
      "node_id": 139,
      "x": 2100.6,
      "y": 1860.0,
      "z": null,
      "demand": 0,
      "is_depot": false,
      "display_x": null,
      "display_y": null
    },
    {
      "node_id": 140,
      "x": 2126.0,
      "y": 1860.0,
      "z": null,
      "demand": 0,
      "is_depot": false,
      "display_x": null,
      "display_y": null
    },
    {
      "node_id": 141,
      "x": 2100.6,
      "y": 1885.4,
      "z": null,
      "demand": 0,
      "is_depot": false,
      "display_x": null,
      "display_y": null
    },
    {
      "node_id": 142,
      "x": 2126.0,
      "y": 1885.4,
      "z": null,
      "demand": 0,
      "is_depot": false,
      "display_x": null,
      "display_y": null
    },
    {
      "node_id": 143,
      "x": 2176.8,
      "y": 1885.4,
      "z": null,
      "demand": 0,
      "is_depot": false,
      "display_x": null,
      "display_y": null
    },
    {
      "node_id": 144,
      "x": 2151.4,
      "y": 1910.8,
      "z": null,
      "demand": 0,
      "is_depot": false,
      "display_x": null,
      "display_y": null
    },
    {
      "node_id": 145,
      "x": 2126.0,
      "y": 1910.8,
      "z": null,
      "demand": 0,
      "is_depot": false,
      "display_x": null,
      "display_y": null
    },
    {
      "node_id": 146,
      "x": 2100.6,
      "y": 1910.8,
      "z": null,
      "demand": 0,
      "is_depot": false,
      "display_x": null,
      "display_y": null
    },
    {
      "node_id": 147,
      "x": 2100.6,
      "y": 1936.2,
      "z": null,
      "demand": 0,
      "is_depot": false,
      "display_x": null,
      "display_y": null
    },
    {
      "node_id": 148,
      "x": 2126.0,
      "y": 1936.2,
      "z": null,
      "demand": 0,
      "is_depot": false,
      "display_x": null,
      "display_y": null
    },
    {
      "node_id": 149,
      "x": 2176.8,
      "y": 1936.2,
      "z": null,
      "demand": 0,
      "is_depot": false,
      "display_x": null,
      "display_y": null
    },
    {
      "node_id": 150,
      "x": 2227.6,
      "y": 1936.2,
      "z": null,
      "demand": 0,
      "is_depot": false,
      "display_x": null,
      "display_y": null
    },
    {
      "node_id": 151,
      "x": 2126.0,
      "y": 1961.6,
      "z": null,
      "demand": 0,
      "is_depot": false,
      "display_x": null,
      "display_y": null
    },
    {
      "node_id": 152,
      "x": 2100.6,
      "y": 1961.6,
      "z": null,
      "demand": 0,
      "is_depot": false,
      "display_x": null,
      "display_y": null
    },
    {
      "node_id": 153,
      "x": 1795.8,
      "y": 1987.0,
      "z": null,
      "demand": 0,
      "is_depot": false,
      "display_x": null,
      "display_y": null
    },
    {
      "node_id": 154,
      "x": 1821.2,
      "y": 1987.0,
      "z": null,
      "demand": 0,
      "is_depot": false,
      "display_x": null,
      "display_y": null
    },
    {
      "node_id": 155,
      "x": 1846.6,
      "y": 1987.0,
      "z": null,
      "demand": 0,
      "is_depot": false,
      "display_x": null,
      "display_y": null
    },
    {
      "node_id": 156,
      "x": 1872.0,
      "y": 1987.0,
      "z": null,
      "demand": 0,
      "is_depot": false,
      "display_x": null,
      "display_y": null
    },
    {
      "node_id": 157,
      "x": 1897.4,
      "y": 1987.0,
      "z": null,
      "demand": 0,
      "is_depot": false,
      "display_x": null,
      "display_y": null
    },
    {
      "node_id": 158,
      "x": 1948.2,
      "y": 1987.0,
      "z": null,
      "demand": 0,
      "is_depot": false,
      "display_x": null,
      "display_y": null
    },
    {
      "node_id": 159,
      "x": 2056.2,
      "y": 1987.0,
      "z": null,
      "demand": 0,
      "is_depot": false,
      "display_x": null,
      "display_y": null
    },
    {
      "node_id": 160,
      "x": 2100.6,
      "y": 1987.0,
      "z": null,
      "demand": 0,
      "is_depot": false,
      "display_x": null,
      "display_y": null
    },
    {
      "node_id": 161,
      "x": 2126.0,
      "y": 1987.0,
      "z": null,
      "demand": 0,
      "is_depot": false,
      "display_x": null,
      "display_y": null
    },
    {
      "node_id": 162,
      "x": 2253.0,
      "y": 1987.0,
      "z": null,
      "demand": 0,
      "is_depot": false,
      "display_x": null,
      "display_y": null
    },
    {
      "node_id": 163,
      "x": 2303.8,
      "y": 1987.0,
      "z": null,
      "demand": 0,
      "is_depot": false,
      "display_x": null,
      "display_y": null
    },
    {
      "node_id": 164,
      "x": 2380.0,
      "y": 1987.0,
      "z": null,
      "demand": 0,
      "is_depot": false,
      "display_x": null,
      "display_y": null
    },
    {
      "node_id": 165,
      "x": 2405.4,
      "y": 1987.0,
      "z": null,
      "demand": 0,
      "is_depot": false,
      "display_x": null,
      "display_y": null
    },
    {
      "node_id": 166,
      "x": 2024.4,
      "y": 1402.8,
      "z": null,
      "demand": 0,
      "is_depot": false,
      "display_x": null,
      "display_y": null
    },
    {
      "node_id": 167,
      "x": 2151.4,
      "y": 1402.8,
      "z": null,
      "demand": 0,
      "is_depot": false,
      "display_x": null,
      "display_y": null
    },
    {
      "node_id": 168,
      "x": 2075.2,
      "y": 1707.6,
      "z": null,
      "demand": 0,
      "is_depot": false,
      "display_x": null,
      "display_y": null
    },
    {
      "node_id": 169,
      "x": 2176.8,
      "y": 1707.6,
      "z": null,
      "demand": 0,
      "is_depot": false,
      "display_x": null,
      "display_y": null
    },
    {
      "node_id": 170,
      "x": 2350.8,
      "y": 1733.0,
      "z": null,
      "demand": 0,
      "is_depot": false,
      "display_x": null,
      "display_y": null
    },
    {
      "node_id": 171,
      "x": 2350.8,
      "y": 1847.3,
      "z": null,
      "demand": 0,
      "is_depot": false,
      "display_x": null,
      "display_y": null
    },
    {
      "node_id": 172,
      "x": 3652.1,
      "y": 1010.3,
      "z": null,
      "demand": 0,
      "is_depot": false,
      "display_x": null,
      "display_y": null
    },
    {
      "node_id": 173,
      "x": 3725.7,
      "y": 1010.3,
      "z": null,
      "demand": 0,
      "is_depot": false,
      "display_x": null,
      "display_y": null
    },
    {
      "node_id": 174,
      "x": 3725.7,
      "y": 1086.5,
      "z": null,
      "demand": 0,
      "is_depot": false,
      "display_x": null,
      "display_y": null
    },
    {
      "node_id": 175,
      "x": 3652.1,
      "y": 1086.5,
      "z": null,
      "demand": 0,
      "is_depot": false,
      "display_x": null,
      "display_y": null
    },
    {
      "node_id": 176,
      "x": 3726.2,
      "y": 1148.8,
      "z": null,
      "demand": 0,
      "is_depot": false,
      "display_x": null,
      "display_y": null
    },
    {
      "node_id": 177,
      "x": 3802.4,
      "y": 1148.8,
      "z": null,
      "demand": 0,
      "is_depot": false,
      "display_x": null,
      "display_y": null
    },
    {
      "node_id": 178,
      "x": 3853.2,
      "y": 1148.8,
      "z": null,
      "demand": 0,
      "is_depot": false,
      "display_x": null,
      "display_y": null
    },
    {
      "node_id": 179,
      "x": 3802.4,
      "y": 1174.2,
      "z": null,
      "demand": 0,
      "is_depot": false,
      "display_x": null,
      "display_y": null
    },
    {
      "node_id": 180,
      "x": 3700.8,
      "y": 1174.2,
      "z": null,
      "demand": 0,
      "is_depot": false,
      "display_x": null,
      "display_y": null
    },
    {
      "node_id": 181,
      "x": 3605.6,
      "y": 1199.6,
      "z": null,
      "demand": 0,
      "is_depot": false,
      "display_x": null,
      "display_y": null
    },
    {
      "node_id": 182,
      "x": 3700.8,
      "y": 1199.6,
      "z": null,
      "demand": 0,
      "is_depot": false,
      "display_x": null,
      "display_y": null
    },
    {
      "node_id": 183,
      "x": 3802.4,
      "y": 1199.6,
      "z": null,
      "demand": 0,
      "is_depot": false,
      "display_x": null,
      "display_y": null
    },
    {
      "node_id": 184,
      "x": 3853.2,
      "y": 1199.6,
      "z": null,
      "demand": 0,
      "is_depot": false,
      "display_x": null,
      "display_y": null
    },
    {
      "node_id": 185,
      "x": 4028.3,
      "y": 1310.3,
      "z": null,
      "demand": 0,
      "is_depot": false,
      "display_x": null,
      "display_y": null
    },
    {
      "node_id": 186,
      "x": 3952.1,
      "y": 1310.3,
      "z": null,
      "demand": 0,
      "is_depot": false,
      "display_x": null,
      "display_y": null
    },
    {
      "node_id": 187,
      "x": 3728.3,
      "y": 1310.3,
      "z": null,
      "demand": 0,
      "is_depot": false,
      "display_x": null,
      "display_y": null
    },
    {
      "node_id": 188,
      "x": 3652.1,
      "y": 1310.3,
      "z": null,
      "demand": 0,
      "is_depot": false,
      "display_x": null,
      "display_y": null
    },
    {
      "node_id": 189,
      "x": 3652.1,
      "y": 1386.5,
      "z": null,
      "demand": 0,
      "is_depot": false,
      "display_x": null,
      "display_y": null
    },
    {
      "node_id": 190,
      "x": 3728.3,
      "y": 1386.5,
      "z": null,
      "demand": 0,
      "is_depot": false,
      "display_x": null,
      "display_y": null
    },
    {
      "node_id": 191,
      "x": 3952.1,
      "y": 1386.5,
      "z": null,
      "demand": 0,
      "is_depot": false,
      "display_x": null,
      "display_y": null
    },
    {
      "node_id": 192,
      "x": 4028.3,
      "y": 1386.5,
      "z": null,
      "demand": 0,
      "is_depot": false,
      "display_x": null,
      "display_y": null
    },
    {
      "node_id": 193,
      "x": 3853.2,
      "y": 1123.4,
      "z": null,
      "demand": 0,
      "is_depot": false,
      "display_x": null,
      "display_y": null
    },
    {
      "node_id": 194,
      "x": 3952.1,
      "y": 1086.5,
      "z": null,
      "demand": 0,
      "is_depot": false,
      "display_x": null,
      "display_y": null
    },
    {
      "node_id": 195,
      "x": 4028.3,
      "y": 1086.5,
      "z": null,
      "demand": 0,
      "is_depot": false,
      "display_x": null,
      "display_y": null
    },
    {
      "node_id": 196,
      "x": 4028.3,
      "y": 1010.3,
      "z": null,
      "demand": 0,
      "is_depot": false,
      "display_x": null,
      "display_y": null
    },
    {
      "node_id": 197,
      "x": 3952.1,
      "y": 1010.3,
      "z": null,
      "demand": 0,
      "is_depot": false,
      "display_x": null,
      "display_y": null
    }
  ],
  "tours": [],
  "metadata": {
    "file_path": "datasets_raw/problems/tsp/d198.tsp",
    "file_size": 5561,
    "file_name": "d198.tsp",
    "problem_source": "tsp",
    "has_coordinates": true,
    "has_demands": false,
    "has_depots": false,
    "is_symmetric": true,
    "weight_source": "coordinate_based"
  }
}