{
  "problem": {
    "name": "ulysses16.tsp",
    "type": "TSP",
    "comment": "Odyssey of Ulysses (Groetschel/Padberg)",
    "dimension": 16,
    "capacity": null,
    "edge_weight_type": "GEO",
    "edge_weight_format": null,
    "node_coord_type": null,
    "display_data_type": "COORD_DISPLAY",
    "file_path": "datasets_raw/problems/tsp/ulysses16.tsp",
    "file_size": 419
  },
  "nodes": [
    {
      "node_id": 0,
      "x": 38.24,
      "y": 20.42,
      "z": null,
      "demand": 0,
      "is_depot": false,
      "display_x": null,
      "display_y": null
    },
    {
      "node_id": 1,
      "x": 39.57,
      "y": 26.15,
      "z": null,
      "demand": 0,
      "is_depot": false,
      "display_x": null,
      "display_y": null
    },
    {
      "node_id": 2,
      "x": 40.56,
      "y": 25.32,
      "z": null,
      "demand": 0,
      "is_depot": false,
      "display_x": null,
      "display_y": null
    },
    {
      "node_id": 3,
      "x": 36.26,
      "y": 23.12,
      "z": null,
      "demand": 0,
      "is_depot": false,
      "display_x": null,
      "display_y": null
    },
    {
      "node_id": 4,
      "x": 33.48,
      "y": 10.54,
      "z": null,
      "demand": 0,
      "is_depot": false,
      "display_x": null,
      "display_y": null
    },
    {
      "node_id": 5,
      "x": 37.56,
      "y": 12.19,
      "z": null,
      "demand": 0,
      "is_depot": false,
      "display_x": null,
      "display_y": null
    },
    {
      "node_id": 6,
      "x": 38.42,
      "y": 13.11,
      "z": null,
      "demand": 0,
      "is_depot": false,
      "display_x": null,
      "display_y": null
    },
    {
      "node_id": 7,
      "x": 37.52,
      "y": 20.44,
      "z": null,
      "demand": 0,
      "is_depot": false,
      "display_x": null,
      "display_y": null
    },
    {
      "node_id": 8,
      "x": 41.23,
      "y": 9.1,
      "z": null,
      "demand": 0,
      "is_depot": false,
      "display_x": null,
      "display_y": null
    },
    {
      "node_id": 9,
      "x": 41.17,
      "y": 13.05,
      "z": null,
      "demand": 0,
      "is_depot": false,
      "display_x": null,
      "display_y": null
    },
    {
      "node_id": 10,
      "x": 36.08,
      "y": -5.21,
      "z": null,
      "demand": 0,
      "is_depot": false,
      "display_x": null,
      "display_y": null
    },
    {
      "node_id": 11,
      "x": 38.47,
      "y": 15.13,
      "z": null,
      "demand": 0,
      "is_depot": false,
      "display_x": null,
      "display_y": null
    },
    {
      "node_id": 12,
      "x": 38.15,
      "y": 15.35,
      "z": null,
      "demand": 0,
      "is_depot": false,
      "display_x": null,
      "display_y": null
    },
    {
      "node_id": 13,
      "x": 37.51,
      "y": 15.17,
      "z": null,
      "demand": 0,
      "is_depot": false,
      "display_x": null,
      "display_y": null
    },
    {
      "node_id": 14,
      "x": 35.49,
      "y": 14.32,
      "z": null,
      "demand": 0,
      "is_depot": false,
      "display_x": null,
      "display_y": null
    },
    {
      "node_id": 15,
      "x": 39.36,
      "y": 19.56,
      "z": null,
      "demand": 0,
      "is_depot": false,
      "display_x": null,
      "display_y": null
    }
  ],
  "tours": [],
  "metadata": {
    "file_path": "datasets_raw/problems/tsp/ulysses16.tsp",
    "file_size": 419,
    "file_name": "ulysses16.tsp",
    "problem_source": "tsp",
    "has_coordinates": true,
    "has_demands": false,
    "has_depots": false,
    "is_symmetric": true,
    "weight_source": "coordinate_based"
  }
}